Workbook

Sheet Grupo Avanza SPA
A1: Libro: Remuneraciones
A2: Empresa: Grupo Avanza SPA (76.008.458-1)
A3: Periodo: Agosto 2026
A4: Fecha Generación: 28/08/2026 a las 02:47PM
A5: 1 | B5: 2 | C5: 3 | D5: 4 | E5: 5 | F5: 6 | G5: 7 | H5: 8 | I5: 9 | J5: 10 | K5: 11 | L5: 12 | M5: 13 | N5: 14 | O5: 15 | P5: 16 | Q5: 17 | R5: 18 | S5: 19 | T5: 20 | U5: 21 | V5: 22 | W5: 23 | X5: 24 | Y5: 25 | Z5: 26 | AA5: 27 | AB5: 28 | AC5: 29 | AD5: 30 | AE5: 31 | AF5: 32 | AG5: 33 | AH5: 34 | AI5: 35 | AJ5: 36 | AK5: 37 | AL5: 38 | AM5: 39 | AN5: 40 | AO5: 41 | AP5: 42 | AQ5: 43 | AR5: 44 | AS5: 45 | AT5: 46 | AU5: 47 | AV5: 48 | AW5: 49 | AX5: 50
A6: RUT | B6: CÓDIGO | C6: AP PATERNO | D6: AP MATERNO | E6: NOMBRES | F6: CARGO | G6: AREA | H6: CENTRO COSTO | I6: DÍAS TRABAJADOS | J6: HORAS SEMANALES | K6: HORAS NO TRABAJADAS | L6: BASE IMP. PREVISIÓN | M6: BASE IMP. CESANTÍA | N6: SUELDO BASE | O6: GRATIFICACIÓN | P6: APORTE ASISTENCIA | Q6: HORAS EXTRAS | R6: ASIGNACIÓN FAMILIAR | S6: ASIGNACIÓN POR TELETRABAJO | T6: ASIGNACIÓN SALA CUNA | U6: ASIGNACIÓN TELEFONÍA E INTERNET | V6: BONO | W6: BONO ESTUDIO | X6: BONO GESTIÓN | Y6: BONO INTERNET | Z6: BONO TELEFONIA | AA6: BONO TRIMESTRAL ACUERDO MARCO | AB6: COLACIÓN | AC6: COMISIONES | AD6: DIFERENCIA BONO | AE6: INCENTIVO TRIMESTRAL CUOTA 3 | AF6: MOVILIZACIÓN | AG6: VIATICO | AH6: TOTAL HABERES | AI6: PREVIS | AJ6: APV | AK6: SALUD | AL6: SALUD VOLUNTARIA | AM6: CESANTÍA | AN6: IMPUESTO | AO6: CUENTA_2 | AP6: ANTICIPO DE REMUNERACIONES | AQ6: CONVENIO FALP | AR6: CUENTA 2 PESOS | AS6: CRÉDITO PERSONAL CAJA LOS ANDES | AT6: PRESTAMO EMPRESA | AU6: PRÉSTAMO EMPRESA | AV6: SEGURO DE VIDA CAJA LOS ANDES | AW6: TOTAL DESCUENTOS | AX6: SUELDO LÍQUIDO | AY6: SOBREGIRO
A7: 16.280.871-0 | B7: F1 | C7: Aguirre | D7: Vásquez | E7: Stefania Alejandra | F7: Coordinador Senior de Cultura y Desarrollo | G7: OUTSOURCING, Codelco Casa Matriz, Codelco Casa Matriz | I7: 30 | J7: 40 | K7: 0 | L7: 2489778 | M7: 2489778 | N7: 1797330 | O7: 219115 | P7: 0 | Q7: 0 | R7: 0 | Y7: 30000 | AA7: 473333 | AB7: 130000 | AF7: 100000 | AH7: 2749778 | AI7: 280598 | AJ7: 0 | AK7: 174284 | AL7: 0 | AM7: 14939 | AN7: 42108 | AO7: 0 | AW7: 511929 | AX7: 2237849 | AY7: =VLOOKUP(A7,'Hoja 1'!A:AX,50,0)-AX7 -> 0
A8: 17.858.538-k | B8: F1 | C8: Alucema | D8: Moraga | E8: Lucía Beatriz | F8: PSICOLOGA | G8: OUTSOURCING, Cia. Minera del Pacifico S.A., Cia. Minera del Pacifico S.A. | H8: 100 | I8: 0 | J8: 40 | K8: 0 | L8: 0 | M8: 0 | N8: 0 | O8: 0 | P8: 0 | Q8: 0 | R8: 0 | AB8: 0 | AF8: 0 | AH8: 0 | AI8: 0 | AJ8: 0 | AK8: 0 | AL8: 0 | AM8: 0 | AN8: 0 | AO8: 0 | AW8: 0 | AX8: 0 | AY8: =VLOOKUP(A8,'Hoja 1'!A:AX,50,0)-AX8 -> 0
A9: 20.231.495-3 | B9: F1 | C9: Aravena | D9: Rodriguez | E9: Claudia Valentina | F9: Coordinador de Cultura y Desarrollo | G9: OUTSOURCING, Codelco Casa Matriz, Codelco Casa Matriz | I9: 30 | J9: 40 | K9: 0 | L9: 2002961 | M9: 2002961 | N9: 1310513 | O9: 219115 | P9: 0 | Q9: 0 | R9: 0 | Y9: 75000 | AA9: 473333 | AB9: 150000 | AF9: 75000 | AH9: 2302961 | AI9: 209510 | AJ9: 5000 | AK9: 140207 | AL9: 0 | AM9: 12018 | AN9: 26959 | AO9: 0 | AR9: 65000 | AW9: 458694 | AX9: 1844267 | AY9: =VLOOKUP(A9,'Hoja 1'!A:AX,50,0)-AX9 -> 0
A10: 18.354.198-6 | B10: F1 | C10: Araya | D10: Cortés | E10: Eduardo Antonio | F10: Programador | G10: Over Head, IT, IT | H10: 100 | I10: 30 | J10: 42 | K10: 0 | L10: 1025146 | M10: 1025146 | N10: 820117 | O10: 205029 | P10: 0 | Q10: 0 | R10: 0 | AB10: 90000 | AF10: 90000 | AH10: 1205146 | AI10: 108460 | AJ10: 0 | AK10: 71760 | AL10: 0 | AM10: 6151 | AN10: 0 | AO10: 0 | AW10: 186371 | AX10: 1018775 | AY10: =VLOOKUP(A10,'Hoja 1'!A:AX,50,0)-AX10 -> 0
A11: 14.027.919-6 | B11: F1 | C11: Bawarshi | D11: Abarzua | E11: Alfonso Ignacio | F11: Director Ejecutivo | G11: Over Head, Administración, Comercial | H11: 1111 | I11: 30 | J11: 44 | K11: 0 | L11: 3678639 | M11: 5526134 | N11: 12365703 | O11: 219115 | P11: 0 | Q11: 0 | R11: 0 | AH11: 12584818 | AI11: 420836 | AJ11: 0 | AK11: 257505 | AL11: 125278 | AM11: 0 | AN11: 2496412 | AO11: 0 | AW11: 3300031 | AX11: 9284787 | AY11: =VLOOKUP(A11,'Hoja 1'!A:AX,50,0)-AX11 -> 0
A12: 17.408.142-5 | B12: F1 | C12: Bawarshi | D12: Abarzua | E12: Gabriela Estefania | F12: Analista Senior DO | G12: Over Head, Administración, Comercial | H12: 1111 | I12: 30 | J12: 42 | K12: 0 | L12: 861875 | M12: 861875 | N12: 689500 | O12: 172375 | P12: 0 | Q12: 0 | R12: 0 | AH12: 861875 | AI12: 96185 | AJ12: 0 | AK12: 60331 | AL12: 156136 | AM12: 5171 | AN12: 0 | AO12: 0 | AW12: 317823 | AX12: 544052 | AY12: =VLOOKUP(A12,'Hoja 1'!A:AX,50,0)-AX12 -> 0
A13: 22.074.650-k | B13: F1 | C13: Bustiman | D13: Gonzalez | E13: Gabriel Bastian | F13: Technician Service Assistance | G13: OUTSOURCING, Endress Hauser, Endress Hauser | H13: 100 | I13: 30 | J13: 44 | K13: 0 | L13: 800000 | M13: 800000 | N13: 640000 | O13: 160000 | P13: 0 | Q13: 0 | R13: 0 | AH13: 800000 | AI13: 83680 | AJ13: 0 | AK13: 56000 | AL13: 0 | AM13: 4800 | AN13: 0 | AO13: 0 | AW13: 144480 | AX13: 655520 | AY13: =VLOOKUP(A13,'Hoja 1'!A:AX,50,0)-AX13 -> 0
A14: 28.830.860-8 | B14: F1 | C14: Camacho | D14: Cordero | E14: Roger Alberto | F14: Gestor de Procesos | G14: OUTSOURCING, Goldfields, Goldfield | H14: 100 | I14: 30 | J14: 40 | K14: 0 | L14: 2500533 | M14: 2500533 | N14: 2281418 | O14: 219115 | P14: 0 | Q14: 0 | R14: 0 | AH14: 2500533 | AI14: 261556 | AJ14: 0 | AK14: 175037 | AL14: 55328 | AM14: 0 | AN14: 41654 | AO14: 0 | AW14: 533575 | AX14: 1966958 | AY14: =VLOOKUP(A14,'Hoja 1'!A:AX,50,0)-AX14 -> 0
A15: 20.043.827-2 | B15: F1 | C15: Cantarero | D15: Pacheco | E15: Elias Matias Ignacio | F15: SERVICE TECHNICIAL | G15: OUTSOURCING, Endress Hauser, Endress Hauser | H15: 100 | I15: 30 | J15: 42 | K15: 0 | L15: 1356403 | M15: 1356403 | N15: 1137288 | O15: 219115 | P15: 0 | Q15: 0 | R15: 0 | AH15: 1356403 | AI15: 143507 | AJ15: 0 | AK15: 94948 | AL15: 0 | AM15: 8138 | AN15: 5702 | AO15: 0 | AW15: 252295 | AX15: 1104108 | AY15: =VLOOKUP(A15,'Hoja 1'!A:AX,50,0)-AX15 -> 0
A16: 20.411.355-6 | B16: F1 | C16: Carreño | D16: Espinoza | E16: Amaranta Paola | F16: Asistente de Gestion de Personas | G16: OUTSOURCING, Cia. Minera del Pacifico S.A., Cia. Minera del Pacifico S.A. | H16: 100 | I16: 29 | J16: 40 | K16: 0 | L16: 1283580 | M16: 1283580 | N16: 1064465 | O16: 219115 | P16: 0 | Q16: 0 | R16: 0 | T16: 350000 | AB16: 43500 | AF16: 43500 | AH16: 1720580 | AI16: 135803 | AJ16: 0 | AK16: 89851 | AL16: 0 | AM16: 7701 | AN16: 3319 | AO16: 0 | AW16: 236674 | AX16: 1483906 | AY16: =VLOOKUP(A16,'Hoja 1'!A:AX,50,0)-AX16 -> -350000
A17: 21.380.747-1 | B17: F1 | C17: Catalan | D17: Mardones | E17: Javiera Alejandra | F17: Asistente Contable | G17: OUTSOURCING, CONTINENTAL SEGUROS, CONTINENTAL SEGUROS | H17: 100 | I17: 30 | J17: 42 | K17: 0 | L17: 847959 | M17: 847959 | N17: 678367 | O17: 169592 | P17: 0 | Q17: 0 | R17: 0 | AB17: 90000 | AF17: 90000 | AH17: 1027959 | AI17: 89714 | AJ17: 0 | AK17: 59357 | AL17: 0 | AM17: 5088 | AN17: 0 | AO17: 0 | AW17: 154159 | AX17: 873800 | AY17: =VLOOKUP(A17,'Hoja 1'!A:AX,50,0)-AX17 -> 0
A18: 19.135.138-k | B18: F1 | C18: Cataldo | D18: Caviedes | E18: Claudia Fernanda | F18: Coordinador de Reclutamiento y Selección | G18: Hunting, Hunting, Hunting | H18: 1111 | I18: 30 | J18: 42 | K18: 0 | L18: 1758961 | M18: 1758961 | N18: 1539846 | O18: 219115 | P18: 0 | Q18: 0 | R18: 0 | AB18: 100000 | AF18: 100000 | AH18: 1958961 | AI18: 186098 | AJ18: 0 | AK18: 123127 | AL18: 1865 | AM18: 10554 | AN18: 18802 | AO18: 0 | AQ18: 19800 | AW18: 360246 | AX18: 1598715 | AY18: =VLOOKUP(A18,'Hoja 1'!A:AX,50,0)-AX18 -> 0
A19: 19.867.384-6 | B19: F1 | C19: Caul | D19: Cortes | E19: Francisca Valentina | F19: Coordinador Avanzado | G19: OUTSOURCING, CODELCO CHILE -V. P., CODELCO CHILE -V. P. | H19: 100 | I19: 30 | J19: 40 | K19: 0 | L19: 2018709 | M19: 2018709 | N19: 1484039 | O19: 219115 | P19: 0 | Q19: 0 | R19: 0 | AB19: 100000 | AE19: 315555 | AF19: 100000 | AH19: 2218709 | AI19: 213579 | AJ19: 0 | AK19: 141310 | AL19: 0 | AM19: 12112 | AN19: 27378 | AO19: 0 | AW19: 394379 | AX19: 1824330 | AY19: =VLOOKUP(A19,'Hoja 1'!A:AX,50,0)-AX19 -> 0
A20: 16.479.434-2 | B20: F1 | C20: Correa | D20: Araya | E20: Camila Denis | F20: KEY ACCOUNT MANAGER SENIOR | G20: Over Head, Administración, Comercial | H20: 1111 | I20: 30 | J20: 42 | K20: 0 | L20: 2071498 | M20: 2071498 | N20: 1852383 | O20: 219115 | P20: 0 | Q20: 0 | R20: 0 | AB20: 80000 | AF20: 80000 | AH20: 2231498 | AI20: 233458 | AJ20: 0 | AK20: 145005 | AL20: 42933 | AM20: 12429 | AN20: 26816 | AO20: 0 | AW20: 460641 | AX20: 1770857 | AY20: =VLOOKUP(A20,'Hoja 1'!A:AX,50,0)-AX20 -> 0
A21: 26.972.625-3 | B21: F1 | C21: De Sousa | D21: Garcia | E21: Stephen William | F21: Control Interno | G21: OUTSOURCING, Goldfields, Goldfield | H21: 100 | I21: 30 | J21: 42 | K21: 0 | L21: 2279115 | M21: 2279115 | N21: 2060000 | O21: 219115 | P21: 0 | Q21: 0 | R21: 0 | AB21: 100000 | AF21: 100000 | AH21: 2479115 | AI21: 238395 | AJ21: 0 | AK21: 159538 | AL21: 89138 | AM21: 13675 | AN21: 32444 | AO21: 0 | AP21: 100000 | AW21: 633190 | AX21: 1845925 | AY21: =VLOOKUP(A21,'Hoja 1'!A:AX,50,0)-AX21 -> 0
A22: 26.304.359-6 | B22: F1 | C22: Diaz | D22: Gonzalez | E22: Fatima | F22: Supervisor Técnico del Servicio | G22: OUTSOURCING, Enap, Enap | H22: 100 | I22: 30 | J22: 37 | K22: 0 | L22: 2816897 | M22: 2816897 | N22: 2597782 | O22: 219115 | P22: 0 | Q22: 0 | R22: 0 | AB22: 280000 | AF22: 280000 | AH22: 3376897 | AI22: 314366 | AJ22: 0 | AK22: 197183 | AL22: 37473 | AM22: 16901 | AN22: 55409 | AO22: 0 | AW22: 621332 | AX22: 2755565 | AY22: =VLOOKUP(A22,'Hoja 1'!A:AX,50,0)-AX22 -> 0
A23: 17.318.383-6 | B23: F1 | C23: Espinoza | D23: Latorre | E23: Daniela Paz Loreto | F23: Especialista en Biodiversidad | G23: OUTSOURCING, Salar Blanco, Salar Blanco | H23: 100 | I23: 22 | J23: 42 | K23: 0 | L23: 3581244 | M23: 3581244 | N23: 3362129 | O23: 219115 | P23: 0 | Q23: 0 | R23: 0 | AH23: 3581244 | AI23: 409694 | AJ23: 0 | AK23: 250687 | AL23: 0 | AM23: 21487 | AN23: 107281 | AO23: 0 | AW23: 789149 | AX23: 2792095 | AY23: =VLOOKUP(A23,'Hoja 1'!A:AX,50,0)-AX23 -> 0
A24: 25.387.977-7 | B24: F1 | C24: Fuentes | D24: Rodriguez | E24: Levy Johan | F24: Especialista Modelamiento | G24: OUTSOURCING, Salar Blanco, Salar Blanco | H24: 100 | I24: 30 | J24: 42 | K24: 0 | L24: 3678639 | M24: 5273749 | N24: 4958453 | O24: 219115 | P24: 0 | Q24: 0 | R24: 0 | AD24: 96181 | AH24: 5273749 | AI24: 420836 | AJ24: 0 | AK24: 257505 | AL24: 74063 | AM24: 0 | AN24: 298676 | AO24: 0 | AW24: 1051080 | AX24: 4222669 | AY24: =VLOOKUP(A24,'Hoja 1'!A:AX,50,0)-AX24 -> 0
A25: 18.585.098-6 | B25: F1 | C25: Garcia | D25: Cruz | E25: Isabel Ivania | F25: Coordinador Senior | G25: OUTSOURCING, CODELCO CHILE -V. P., CODELCO CHILE -V. P. | H25: 100 | I25: 30 | J25: 40 | K25: 0 | L25: 3678639 | M25: 3696162 | N25: 3003714 | O25: 219115 | P25: 0 | Q25: 0 | R25: 0 | AB25: 100000 | AE25: 473333 | AF25: 100000 | AH25: 3896162 | AI25: 414583 | AJ25: 0 | AK25: 257505 | AL25: 0 | AM25: 22177 | AN25: 115482 | AO25: 0 | AQ25: 19800 | AW25: 829547 | AX25: 3066615 | AY25: =VLOOKUP(A25,'Hoja 1'!A:AX,50,0)-AX25 -> 0
A26: 21.166.392-8 | B26: F1 | C26: Garcia | D26: Soria | E26: Alexis Joshua | F26: Especialista en Sistemas | G26: OUTSOURCING, Enap, Enap | H26: 100 | I26: 30 | J26: 37 | K26: 0 | L26: 2399470 | M26: 2399470 | N26: 2180355 | O26: 219115 | P26: 0 | Q26: 0 | R26: 0 | AB26: 250000 | AF26: 250000 | AH26: 2899470 | AI26: 250985 | AJ26: 0 | AK26: 167963 | AL26: 0 | AM26: 14397 | AN26: 39955 | AO26: 0 | AW26: 473300 | AX26: 2426170 | AY26: =VLOOKUP(A26,'Hoja 1'!A:AX,50,0)-AX26 -> 0
A27: 17.852.693-6 | B27: F1 | C27: Gil | D27: Salazar | E27: Ivan Ignacio | F27: SERVICE TECHNICIAL | G27: OUTSOURCING, Endress Hauser, Endress Hauser | H27: 100 | I27: 30 | J27: 42 | K27: 0 | L27: 1356403 | M27: 1356403 | N27: 1137288 | O27: 219115 | P27: 0 | Q27: 0 | R27: 0 | AH27: 1356403 | AI27: 143507 | AJ27: 0 | AK27: 94948 | AL27: 0 | AM27: 8138 | AN27: 5702 | AO27: 0 | AW27: 252295 | AX27: 1104108 | AY27: =VLOOKUP(A27,'Hoja 1'!A:AX,50,0)-AX27 -> 0
A28: 18.668.865-1 | B28: F1 | C28: Gomez | D28: Paris | E28: Rodrigo Ignacio | F28: Coordinador Senior de Cultura y Desarrollo | G28: OUTSOURCING, Codelco Casa Matriz, Codelco Casa Matriz | I28: 30 | J28: 40 | K28: 0 | L28: 2534485 | M28: 2534485 | N28: 1684259 | O28: 219115 | P28: 0 | Q28: 0 | R28: 0 | Y28: 30000 | AA28: 631111 | AB28: 170000 | AF28: 170000 | AH28: 2904485 | AI28: 268149 | AJ28: 0 | AK28: 177414 | AL28: 0 | AM28: 15207 | AN28: 44258 | AO28: 0 | AW28: 505028 | AX28: 2399457 | AY28: =VLOOKUP(A28,'Hoja 1'!A:AX,50,0)-AX28 -> 0
A29: 15.934.450-9 | B29: F1 | C29: Gonzalez | D29: Muñoz | E29: Viviana Soledad | F29: Gerente Comercial | G29: Over Head, Administración, Comercial | H29: 1111 | I29: 30 | J29: 44 | K29: 0 | L29: 3678639 | M29: 3953939 | N29: 3734824 | O29: 219115 | P29: 0 | Q29: 0 | R29: 0 | T29: 600000 | AB29: 200000 | AF29: 200000 | AH29: 4953939 | AI29: 420836 | AJ29: 0 | AK29: 257505 | AL29: 129079 | AM29: 23724 | AN29: 135481 | AO29: 0 | AQ29: 19800 | AW29: 986425 | AX29: 3967514 | AY29: =VLOOKUP(A29,'Hoja 1'!A:AX,50,0)-AX29 -> 0
A30: 19.928.652-8 | B30: F1 | C30: Guerrero | D30: Maldonado | E30: Geraldine | F30: Coordinadora Avanzada | G30: OUTSOURCING, CODELCO CHILE -V. P., CODELCO CHILE -V. P. | H30: 100 | I30: 30 | J30: 40 | K30: 0 | L30: 2176352 | M30: 2176352 | N30: 1483904 | O30: 219115 | P30: 0 | Q30: 0 | R30: 0 | AB30: 100000 | AE30: 473333 | AF30: 100000 | AH30: 2376352 | AI30: 227646 | AJ30: 0 | AK30: 152345 | AL30: 0 | AM30: 13058 | AN30: 32642 | AO30: 0 | AW30: 425691 | AX30: 1950661 | AY30: =VLOOKUP(A30,'Hoja 1'!A:AX,50,0)-AX30 -> 0
A31: 16.477.999-8 | B31: F1 | C31: Gutiérrez | D31: Castro | E31: Carolina Arlette | F31: Analista de Logística JR | G31: OUTSOURCING, Tesa Tape Chile S.A., Tesa Tape Chile S.A. | H31: 100 | I31: 30 | J31: 42 | K31: 0 | L31: 1596165 | M31: 1596165 | N31: 1358500 | O31: 219115 | P31: 0 | Q31: 0 | R31: 0 | V31: 18550 | AH31: 1596165 | AI31: 182601 | AJ31: 0 | AK31: 111732 | AL31: 0 | AM31: 9577 | AN31: 13000 | AO31: 0 | AW31: 316910 | AX31: 1279255 | AY31: =VLOOKUP(A31,'Hoja 1'!A:AX,50,0)-AX31 -> 0
A32: 15.737.550-4 | B32: F1 | C32: Hurtado | D32: Canto | E32: Alejandro Eduardo | F32: Coordinador Senior | G32: OUTSOURCING, CODELCO CHILE -V. P., CODELCO CHILE -V. P. | H32: 100 | I32: 30 | J32: 42 | K32: 0 | L32: 3351652 | M32: 3351652 | N32: 2816982 | O32: 219115 | P32: 0 | Q32: 0 | R32: 0 | AB32: 100000 | AE32: 315555 | AF32: 100000 | AH32: 3551652 | AI32: 377731 | AJ32: 0 | AK32: 234616 | AL32: 16921 | AM32: 20110 | AN32: 91513 | AO32: 0 | AS32: 385837 | AW32: 1126728 | AX32: 2424924 | AY32: =VLOOKUP(A32,'Hoja 1'!A:AX,50,0)-AX32 -> 0
A33: 18.467.232-4 | B33: F1 | C33: Jamis | D33: Matus | E33: Juan Ignacio | F33: Gerente de Clientes y Licitaciones | G33: Over Head, Administración, Comercial | H33: 1111 | I33: 30 | J33: 44 | K33: 0 | L33: 2860189 | M33: 2860189 | N33: 2641074 | O33: 219115 | P33: 0 | Q33: 0 | R33: 0 | AB33: 150000 | AF33: 150000 | AH33: 3160189 | AI33: 302608 | AJ33: 0 | AK33: 200213 | AL33: 0 | AM33: 17161 | AN33: 62547 | AO33: 0 | AQ33: 19800 | AW33: 602329 | AX33: 2557860 | AY33: =VLOOKUP(A33,'Hoja 1'!A:AX,50,0)-AX33 -> 0
A34: 15.805.887-1 | B34: F1 | C34: Jara | D34: Ochoa | E34: Jacqueline Carolina | F34: Asesor Senior de Prevención de Riesgos | G34: OUTSOURCING, CODELCO, Modulo 2 | I34: 30 | J34: 42 | K34: 0 | L34: 2748807 | M34: 2748807 | N34: 2056359 | O34: 219115 | P34: 0 | Q34: 0 | R34: 0 | Y34: 125000 | AA34: 473333 | AB34: 250000 | AF34: 250000 | AH34: 3373807 | AI34: 309791 | AJ34: 0 | AK34: 192416 | AL34: 1080 | AM34: 16493 | AN34: 53653 | AO34: 0 | AS34: 186081 | AW34: 759514 | AX34: 2614293 | AY34: =VLOOKUP(A34,'Hoja 1'!A:AX,50,0)-AX34 -> 0
A35: 13.462.122-2 | B35: F1 | C35: Labraña | D35: Gutierrez | E35: Maria Carolina | F35: Coordinador Experto | G35: OUTSOURCING, CODELCO CHILE -V. P., CODELCO CHILE -V. P. | H35: 100 | I35: 30 | J35: 42 | K35: 0 | L35: 3678639 | M35: 4263081 | N35: 3570633 | O35: 219115 | P35: 0 | Q35: 0 | R35: 0 | AB35: 100000 | AE35: 473333 | AF35: 100000 | AH35: 4463081 | AI35: 414583 | AJ35: 0 | AK35: 257505 | AL35: 1471 | AM35: 25578 | AN35: 160564 | AO35: 0 | AS35: 29854 | AW35: 889555 | AX35: 3573526 | AY35: =VLOOKUP(A35,'Hoja 1'!A:AX,50,0)-AX35 -> 0
A36: 13.035.195-6 | B36: F1 | C36: La Roche | D36: Benitez | E36: Udo Franz | F36: ASSET OPTIMIZATION | G36: OUTSOURCING, Goldfields, Goldfield | H36: 100 | I36: 30 | J36: 40 | K36: 0 | L36: 3678639 | M36: 4328779 | N36: 4109664 | O36: 219115 | P36: 0 | Q36: 0 | R36: 0 | AH36: 4328779 | AI36: 414583 | AJ36: 0 | AK36: 257505 | AL36: 306471 | AM36: 25973 | AN36: 168443 | AO36: 0 | AW36: 1172975 | AX36: 3155804 | AY36: =VLOOKUP(A36,'Hoja 1'!A:AX,50,0)-AX36 -> 0
A37: 20.465.683-5 | B37: F1 | C37: Morales | D37: Valdes | E37: Barbara Jesus | F37: Marketing Analyst | G37: OUTSOURCING, EDGEWELL CHILE, EDGEWELL CHILE | H37: 100 | I37: 21 | J37: 40 | K37: 0 | L37: 1615615 | M37: 1615615 | N37: 1396500 | O37: 219115 | P37: 0 | Q37: 0 | R37: 0 | S37: 7000 | U37: 14000 | AH37: 1636615 | AI37: 170932 | AJ37: 0 | AK37: 113093 | AL37: 21839 | AM37: 9694 | AN37: 13312 | AO37: 0 | AW37: 328870 | AX37: 1307745 | AY37: =VLOOKUP(A37,'Hoja 1'!A:AX,50,0)-AX37 -> 0
A38: 16.163.207-4 | B38: F1 | C38: Morrison | D38: Robles | E38: Dawn Faye | F38: Asistente Comercial Bilingue | G38: Over Head, Administración, Comercial | H38: 1111 | I38: 30 | J38: 44 | K38: 0 | L38: 2586937 | M38: 2586937 | N38: 2367822 | O38: 219115 | P38: 0 | Q38: 0 | R38: 0 | AH38: 2586937 | AI38: 288702 | AJ38: 0 | AK38: 181086 | AL38: 408028 | AM38: 15522 | AN38: 42318 | AO38: 0 | AW38: 935656 | AX38: 1651281 | AY38: =VLOOKUP(A38,'Hoja 1'!A:AX,50,0)-AX38 -> 0
A39: 15.475.910-7 | B39: F1 | C39: Muñoz | D39: Gonzalez | E39: Jocelyn Andrea | F39: Receptionist & Administrative Assistant | G39: OUTSOURCING, Endress Hauser, Endress Hauser | H39: 100 | I39: 3 | J39: 40 | K39: 0 | L39: 183941 | M39: 183941 | N39: 147153 | O39: 36788 | P39: 0 | Q39: 0 | R39: 0 | AH39: 183941 | AI39: 21043 | AJ39: 0 | AK39: 12876 | AL39: 0 | AM39: 1104 | AN39: 0 | AO39: 0 | AQ39: 29700 | AW39: 64723 | AX39: 119218 | AY39: =VLOOKUP(A39,'Hoja 1'!A:AX,50,0)-AX39 -> 0
A40: 18.057.004-7 | B40: F1 | C40: Muñoz | D40: Matamala | E40: Denisse Ninoska | F40: SERVICE ASSISTANT | G40: OUTSOURCING, Endress Hauser, Endress Hauser | H40: 100 | I40: 30 | J40: 42 | K40: 0 | L40: 1700761 | M40: 1700761 | N40: 1481646 | O40: 219115 | P40: 0 | Q40: 0 | R40: 0 | AH40: 1700761 | AI40: 179941 | AJ40: 0 | AK40: 119053 | AL40: 0 | AM40: 10205 | AN40: 16972 | AO40: 0 | AW40: 326171 | AX40: 1374590 | AY40: =VLOOKUP(A40,'Hoja 1'!A:AX,50,0)-AX40 -> 0
A41: 20.047.644-1 | B41: F1 | C41: Muñoz | D41: Muñoz | E41: Hernán Stefano | F41: Jefe de Administración y Control de Gestión | G41: Over Head, Administración, Comercial | H41: 1111 | I41: 30 | J41: 42 | K41: 0 | L41: 1235115 | M41: 1235115 | N41: 1016000 | O41: 219115 | P41: 0 | Q41: 0 | R41: 0 | Y41: 15000 | AB41: 50000 | AF41: 50000 | AH41: 1350115 | AI41: 129193 | AJ41: 0 | AK41: 86458 | AL41: 0 | AM41: 7411 | AN41: 1792 | AO41: 0 | AS41: 74207 | AU41: 50000 | AW41: 349061 | AX41: 1001054 | AY41: =VLOOKUP(A41,'Hoja 1'!A:AX,50,0)-AX41 -> 0
A42: 18.445.816-0 | B42: F1 | C42: Muñoz | D42: Pardo | E42: Sebastian Andres | F42: Ingeniero Senior | G42: OUTSOURCING, CODELCO, Modulo 2 | I42: 30 | J42: 42 | K42: 0 | L42: 3678639 | M42: 3768212 | N42: 3075764 | O42: 219115 | P42: 0 | Q42: 0 | R42: 0 | Y42: 100000 | AA42: 473333 | AB42: 387500 | AF42: 387500 | AH42: 4643212 | AI42: 389200 | AJ42: 0 | AK42: 257505 | AL42: 0 | AM42: 22609 | AN42: 123243 | AO42: 0 | AW42: 792557 | AX42: 3850655 | AY42: =VLOOKUP(A42,'Hoja 1'!A:AX,50,0)-AX42 -> 0
A43: 21.081.959-2 | B43: F1 | C43: Muñoz | D43: Parra | E43: Martín Alejandro | F43: Responsable de RRHH y Apoyo en Control de Gestión | G43: Over Head, Administración, Comercial | H43: 1111 | I43: 30 | J43: 41 | K43: 0 | L43: 714199 | M43: 714199 | N43: 571359 | O43: 142840 | P43: 0 | Q43: 0 | R43: 0 | Y43: 15000 | AB43: 50000 | AF43: 50000 | AH43: 829199 | AI43: 74705 | AJ43: 0 | AK43: 49994 | AL43: 0 | AM43: 4285 | AN43: 0 | AO43: 0 | AW43: 128984 | AX43: 700215 | AY43: =VLOOKUP(A43,'Hoja 1'!A:AX,50,0)-AX43 -> 0
A44: 16.642.221-3 | B44: F1 | C44: Muñoz | D44: Vasquez | E44: Camila Yanara | F44: Consultor Senior de Desarrollo | G44: OUTSOURCING, Codelco Casa Matriz, Codelco Casa Matriz | I44: 30 | J44: 40 | K44: 0 | L44: 3047082 | M44: 3047082 | N44: 2354634 | O44: 219115 | P44: 0 | Q44: 0 | R44: 0 | Y44: 35000 | AA44: 473333 | AB44: 250000 | AF44: 215000 | AH44: 3547082 | AI44: 343406 | AJ44: 0 | AK44: 213296 | AL44: 0 | AM44: 18282 | AN44: 73099 | AO44: 0 | AW44: 648083 | AX44: 2898999 | AY44: =VLOOKUP(A44,'Hoja 1'!A:AX,50,0)-AX44 -> 0
A45: 15.310.116-7 | B45: F1 | C45: Narea | D45: Biscupovich | E45: Maria Paz | F45: CONSULTOR SENIOR | G45: OUTSOURCING, Codelco Casa Matriz, Codelco Casa Matriz | I45: 30 | J45: 40 | K45: 0 | L45: 3654524 | M45: 3654524 | N45: 2804298 | O45: 219115 | P45: 0 | Q45: 0 | R45: 0 | Y45: 35000 | AA45: 631111 | AB45: 290000 | AF45: 255000 | AH45: 4234524 | AI45: 411865 | AJ45: 0 | AK45: 255817 | AL45: 0 | AM45: 21927 | AN45: 112524 | AO45: 0 | AW45: 802133 | AX45: 3432391 | AY45: =VLOOKUP(A45,'Hoja 1'!A:AX,50,0)-AX45 -> 0
A46: 13.792.103-0 | B46: F1 | C46: Neira | D46: Molina | E46: Leonardo David | F46: Ingeniero Proyectos | G46: OUTSOURCING, Enap, Enap | H46: 100 | I46: 30 | J46: 37 | K46: 0 | L46: 2501208 | M46: 2501208 | N46: 2282093 | O46: 219115 | P46: 0 | Q46: 0 | R46: 0 | AB46: 250000 | AF46: 250000 | AH46: 3001208 | AI46: 281886 | AJ46: 0 | AK46: 175085 | AL46: 0 | AM46: 15007 | AN46: 42479 | AO46: 0 | AW46: 514457 | AX46: 2486751 | AY46: =VLOOKUP(A46,'Hoja 1'!A:AX,50,0)-AX46 -> 0
A47: 19.983.000-7 | B47: F1 | C47: Nuñez | D47: Gonzales | E47: Pablo Ignacio | F47: Analista Supply Planning | G47: OUTSOURCING, Tesa Tape Chile S.A., Tesa Tape Chile S.A. | H47: 100 | I47: 12 | J47: 40 | K47: 0 | L47: 724670 | M47: 724670 | N47: 579736 | O47: 144934 | P47: 0 | Q47: 0 | R47: 0 | AH47: 724670 | AI47: 82975 | AJ47: 0 | AK47: 50727 | AL47: 0 | AM47: 0 | AN47: 0 | AO47: 0 | AW47: 133702 | AX47: 590968 | AY47: =VLOOKUP(A47,'Hoja 1'!A:AX,50,0)-AX47 -> 0
A48: 18.300.849-8 | B48: F1 | C48: Nuñez | D48: Vazquez | E48: Giselle Andrea | F48: Asesor Senior de Prevención de Riesgos | G48: OUTSOURCING, CODELCO, Modulo 2 | I48: 30 | J48: 42 | K48: 0 | L48: 2748807 | M48: 2748807 | N48: 2056359 | O48: 219115 | P48: 0 | Q48: 0 | R48: 0 | Y48: 125000 | AA48: 473333 | AB48: 250000 | AF48: 250000 | AH48: 3373807 | AI48: 314464 | AJ48: 0 | AK48: 192416 | AL48: 0 | AM48: 16493 | AN48: 53365 | AO48: 0 | AW48: 576738 | AX48: 2797069 | AY48: =VLOOKUP(A48,'Hoja 1'!A:AX,50,0)-AX48 -> 0
A49: 18.416.923-1 | B49: F1 | C49: Ojeda | D49: Islas | E49: Esteban Neftali | F49: Gestor Planificación y Control | G49: OUTSOURCING, Enap, Enap | H49: 100 | I49: 30 | J49: 37 | K49: 0 | L49: 2501208 | M49: 2501208 | N49: 2282093 | O49: 219115 | P49: 0 | Q49: 0 | R49: 0 | AB49: 250000 | AF49: 250000 | AH49: 3001208 | AI49: 264628 | AJ49: 0 | AK49: 175085 | AL49: 0 | AM49: 15007 | AN49: 43169 | AO49: 0 | AW49: 497889 | AX49: 2503319 | AY49: =VLOOKUP(A49,'Hoja 1'!A:AX,50,0)-AX49 -> 0
A50: 15.084.306-5 | B50: F1 | C50: Orellana | D50: Gonzalez | E50: Gabriel Ivan | F50: Ingeniero Senior | G50: OUTSOURCING, CODELCO, Modulo 2 | I50: 30 | J50: 42 | K50: 0 | L50: 3678639 | M50: 3768212 | N50: 3075764 | O50: 219115 | P50: 0 | Q50: 0 | R50: 0 | Y50: 100000 | AA50: 473333 | AB50: 387500 | AF50: 387500 | AH50: 4643212 | AI50: 414583 | AJ50: 0 | AK50: 257505 | AL50: 0 | AM50: 22609 | AN50: 121212 | AO50: 0 | AS50: 11860 | AV50: 34187 | AW50: 861956 | AX50: 3781256 | AY50: =VLOOKUP(A50,'Hoja 1'!A:AX,50,0)-AX50 -> 0
A51: 16.038.646-0 | B51: F1 | C51: Osorio | D51: Petersen | E51: Marcos Felipe | F51: Ingeniero Proyectos | G51: OUTSOURCING, Enap, Enap | H51: 100 | I51: 30 | J51: 37 | K51: 0 | L51: 2621208 | M51: 2621208 | N51: 2402093 | O51: 219115 | P51: 0 | Q51: 0 | R51: 0 | AB51: 190000 | AF51: 190000 | AH51: 3001208 | AI51: 277324 | AJ51: 0 | AK51: 183485 | AL51: 0 | AM51: 15727 | AN51: 47096 | AO51: 0 | AW51: 523632 | AX51: 2477576 | AY51: =VLOOKUP(A51,'Hoja 1'!A:AX,50,0)-AX51 -> 0
A52: 17.392.078-4 | B52: F1 | C52: Pallauta | D52: Rossel | E52: Sergio Antonio | F52: Ingeniero Senior de Proyecto | G52: OUTSOURCING, CODELCO, Modulo 2 | I52: 30 | J52: 42 | K52: 0 | L52: 3678639 | M52: 3752909 | N52: 3060461 | O52: 219115 | P52: 0 | Q52: 0 | R52: 0 | Y52: 100000 | AA52: 473333 | AB52: 387500 | AF52: 387500 | AH52: 4627909 | AI52: 389200 | AJ52: 0 | AK52: 257505 | AL52: 0 | AM52: 22517 | AN52: 122026 | AO52: 0 | AW52: 791248 | AX52: 3836661 | AY52: =VLOOKUP(A52,'Hoja 1'!A:AX,50,0)-AX52 -> 0
A53: 14.120.765-2 | B53: F1 | C53: Paredes | D53: Werth | E53: Macarena Paz | F53: Asistente Administrativa | G53: OUTSOURCING, EDGEWELL CHILE, EDGEWELL CHILE | H53: 100 | I53: 30 | J53: 42 | K53: 0 | L53: 1231897 | M53: 1231897 | N53: 1012782 | O53: 219115 | P53: 0 | Q53: 0 | R53: 0 | U53: 20000 | AH53: 1251897 | AI53: 141052 | AJ53: 0 | AK53: 86233 | AL53: 0 | AM53: 7391 | AN53: 1198 | AO53: 0 | AQ53: 19800 | AW53: 255674 | AX53: 996223 | AY53: =VLOOKUP(A53,'Hoja 1'!A:AX,50,0)-AX53 -> 0
A54: 19.704.689-9 | B54: F1 | C54: Paz | D54: Martinez | E54: Camila Adriana | F54: Consultor Senior Desempeño | G54: OUTSOURCING, Codelco Casa Matriz, Codelco Casa Matriz | I54: 30 | J54: 40 | K54: 0 | L54: 3058855 | M54: 3058855 | N54: 2366407 | O54: 219115 | P54: 0 | Q54: 0 | R54: 0 | Y54: 35000 | AA54: 473333 | AB54: 250000 | AF54: 215000 | AH54: 3558855 | AI54: 319956 | AJ54: 0 | AK54: 214120 | AL54: 0 | AM54: 18353 | AN54: 75845 | AO54: 0 | AS54: 368400 | AW54: 996674 | AX54: 2562181 | AY54: =VLOOKUP(A54,'Hoja 1'!A:AX,50,0)-AX54 -> 0
A55: 15.635.202-0 | B55: F1 | C55: Peña | D55: Ávalos | E55: Macarena Del Pilar | F55: PSICOLOGA | G55: OUTSOURCING, Cia. Minera del Pacifico S.A., Cia. Minera del Pacifico S.A. | H55: 100 | I55: 30 | J55: 40 | K55: 0 | L55: 2193260 | M55: 2193260 | N55: 1974145 | O55: 219115 | P55: 0 | Q55: 0 | R55: 0 | T55: 350000 | U55: 25000 | AB55: 165000 | AF55: 150000 | AH55: 2883260 | AI55: 250909 | AJ55: 0 | AK55: 153528 | AL55: 0 | AM55: 13160 | AN55: 32336 | AO55: 0 | AW55: 449933 | AX55: 2433327 | AY55: =VLOOKUP(A55,'Hoja 1'!A:AX,50,0)-AX55 -> 0
A56: 12.693.080-1 | B56: F1 | C56: Perez | D56: Miranda | E56: Jose Antonio | F56: Ingeniero Senior | G56: OUTSOURCING, CODELCO, Modulo 2 | I56: 30 | J56: 42 | K56: 0 | L56: 3678639 | M56: 3768212 | N56: 3075764 | O56: 219115 | P56: 0 | Q56: 0 | R56: 0 | Y56: 100000 | AA56: 473333 | AB56: 387500 | AF56: 387500 | AH56: 4643212 | AI56: 414583 | AJ56: 0 | AK56: 257505 | AL56: 0 | AM56: 22609 | AN56: 121212 | AO56: 0 | AW56: 815909 | AX56: 3827303 | AY56: =VLOOKUP(A56,'Hoja 1'!A:AX,50,0)-AX56 -> 0
A57: 22.335.317-7 | B57: F1 | C57: Pinto | D57: Guillen | E57: Carlos Enrique | F57: SUPERINTENDENTE DE CONTRATOS | G57: OUTSOURCING, Goldfields, Goldfield | H57: 100 | I57: 30 | J57: 40 | K57: 0 | L57: 3678639 | M57: 5526134 | N57: 5396846 | O57: 219115 | P57: 0 | Q57: 0 | R57: 0 | AH57: 5615961 | AI57: 414583 | AJ57: 0 | AK57: 257505 | AL57: 343585 | AM57: 33157 | AN57: 341243 | AO57: 0 | AW57: 1390073 | AX57: 4225888 | AY57: =VLOOKUP(A57,'Hoja 1'!A:AX,50,0)-AX57 -> 0
A58: 16.822.048-0 | B58: F1 | C58: Quiroz | D58: Garcia | E58: Jose Miguel | F58: Especialista de Planificación | G58: OUTSOURCING, Salar Blanco, Salar Blanco | H58: 100 | I58: 30 | J58: 42 | K58: 0 | L58: 3678639 | M58: 3773058 | N58: 3553943 | O58: 219115 | P58: 0 | Q58: 0 | R58: 0 | AH58: 3773058 | AI58: 389200 | AJ58: 0 | AK58: 257505 | AL58: 0 | AM58: 0 | AN58: 125439 | AO58: 0 | AW58: 772144 | AX58: 3000914 | AY58: =VLOOKUP(A58,'Hoja 1'!A:AX,50,0)-AX58 -> 0
A59: 10.112.634-k | B59: F1 | C59: Ramos | D59: Padilla | E59: Eusebio Hernan | F59: Gestor de Materiales | G59: OUTSOURCING, Enap, Enap | H59: 100 | I59: 30 | J59: 37 | K59: 0 | L59: 1687306 | M59: 1687306 | N59: 1468191 | O59: 219115 | P59: 0 | Q59: 0 | R59: 0 | AB59: 170000 | AF59: 170000 | AH59: 2027306 | AI59: 193028 | AJ59: 0 | AK59: 118111 | AL59: 0 | AM59: 10124 | AN59: 15951 | AO59: 0 | AW59: 337214 | AX59: 1690092 | AY59: =VLOOKUP(A59,'Hoja 1'!A:AX,50,0)-AX59 -> 0
A60: 13.601.169-3 | B60: F1 | C60: Riquelme | D60: Riquelme | E60: José Alejandro | F60: Logistics Analyst & Customer Service | G60: OUTSOURCING, Tesa Tape Chile S.A., Tesa Tape Chile S.A. | H60: 100 | I60: 30 | J60: 42 | K60: 0 | L60: 2309115 | M60: 2309115 | N60: 2090000 | O60: 219115 | P60: 0 | Q60: 0 | R60: 0 | Y60: 18550 | AH60: 2327665 | AI60: 264394 | AJ60: 0 | AK60: 161638 | AL60: 100894 | AM60: 13855 | AN60: 32244 | AO60: 0 | AS60: 247037 | AW60: 820062 | AX60: 1507603 | AY60: =VLOOKUP(A60,'Hoja 1'!A:AX,50,0)-AX60 -> 0
A61: 19.763.405-7 | B61: F1 | C61: Rivera | D61: Soto | E61: Sofia Elena | F61: CONSULTOR SENIOR | G61: OUTSOURCING, Codelco Casa Matriz, Codelco Casa Matriz | I61: 30 | J61: 40 | K61: 0 | L61: 3216633 | M61: 3216633 | N61: 2366407 | O61: 219115 | P61: 0 | Q61: 0 | R61: 0 | Y61: 35000 | AA61: 631111 | AB61: 250000 | AF61: 215000 | AH61: 3716633 | AI61: 340320 | AJ61: 0 | AK61: 225164 | AL61: 30297 | AM61: 19300 | AN61: 83455 | AO61: 0 | AW61: 698536 | AX61: 3018097 | AY61: =VLOOKUP(A61,'Hoja 1'!A:AX,50,0)-AX61 -> 0
A62: 16.435.477-6 | B62: F1 | C62: Rivera | D62: Zapata | E62: Julio Pablo | F62: Supervisor Relacionamiento Comunitario | G62: OUTSOURCING, Salar Blanco, Salar Blanco | H62: 100 | I62: 30 | J62: 44 | K62: 0 | L62: 3678639 | M62: 5489373 | N62: 5270258 | O62: 219115 | P62: 0 | Q62: 0 | R62: 0 | AH62: 5489373 | AI62: 384786 | AJ62: 0 | AK62: 257505 | AL62: 0 | AM62: 32936 | AN62: 328206 | AO62: 0 | AW62: 1003433 | AX62: 4485940 | AY62: =VLOOKUP(A62,'Hoja 1'!A:AX,50,0)-AX62 -> 0
A63: 13.973.575-7 | B63: F1 | C63: Rojas | D63: Malebran | E63: Angelo Mauricio | F63: Contador Financiero | G63: OUTSOURCING, Goldfields, Goldfield | H63: 100 | I63: 30 | J63: 42 | K63: 0 | L63: 3678639 | M63: 4680929 | N63: 4461814 | O63: 219115 | P63: 0 | Q63: 0 | R63: 0 | AB63: 250000 | AF63: 250000 | AH63: 5180929 | AI63: 414583 | AJ63: 0 | AK63: 257505 | AL63: 31881 | AM63: 28086 | AN63: 215698 | AO63: 0 | AW63: 947753 | AX63: 4233176 | AY63: =VLOOKUP(A63,'Hoja 1'!A:AX,50,0)-AX63 -> 0
A64: 17.115.492-8 | B64: F1 | C64: Rojas | D64: Vega | E64: Mayra Arlene | F64: Asesor Senior de Prevención de Riesgos | G64: OUTSOURCING, CODELCO, Modulo 2 | I64: 30 | J64: 42 | K64: 0 | L64: 3049793 | M64: 3049793 | N64: 2357345 | O64: 219115 | P64: 0 | Q64: 0 | R64: 0 | Y64: 100000 | AA64: 473333 | AB64: 300000 | AF64: 300000 | AH64: 3749793 | AI64: 343712 | AJ64: 0 | AK64: 213486 | AL64: 0 | AM64: 18299 | AN64: 73274 | AO64: 0 | AP64: 780000 | AS64: 79490 | AW64: 1508261 | AX64: 2241532 | AY64: =VLOOKUP(A64,'Hoja 1'!A:AX,50,0)-AX64 -> 0
A65: 11.516.219-5 | B65: F1 | C65: Roman | D65: Muñoz | E65: Hugo Alfredo | F65: Especialista en Biodiversidad | G65: OUTSOURCING, Salar Blanco, Salar Blanco | H65: 100 | I65: 30 | J65: 40 | K65: 0 | L65: 3678639 | M65: 5142553 | N65: 4923438 | O65: 219115 | P65: 0 | Q65: 0 | R65: 0 | AH65: 5142553 | AI65: 420836 | AJ65: 0 | AK65: 257505 | AL65: 0 | AM65: 30855 | AN65: 276799 | AO65: 0 | AW65: 985995 | AX65: 4156558 | AY65: =VLOOKUP(A65,'Hoja 1'!A:AX,50,0)-AX65 -> 0
A66: 16.213.156-7 | B66: F1 | C66: Sáez | D66: Correa | E66: Juan Pablo | F66: Gerente de Sistema y Tecnología | G66: Over Head, IT, IT | H66: 100 | I66: 30 | J66: 44 | K66: 0 | L66: 3180336 | M66: 3180336 | N66: 2961221 | O66: 219115 | P66: 0 | Q66: 0 | R66: 0 | AB66: 200000 | AF66: 200000 | AH66: 3580336 | AI66: 363830 | AJ66: 0 | AK66: 222624 | AL66: 42974 | AM66: 19082 | AN66: 78524 | AO66: 0 | AW66: 727034 | AX66: 2853302 | AY66: =VLOOKUP(A66,'Hoja 1'!A:AX,50,0)-AX66 -> 0
A67: 15.014.481-7 | B67: F1 | C67: Sarria | D67: Briceño | E67: Manuel Brayan | F67: Ingeniero Senior | G67: OUTSOURCING, CODELCO, Modulo 2 | I67: 30 | J67: 42 | K67: 0 | L67: 3678639 | M67: 3768212 | N67: 3075764 | O67: 219115 | P67: 0 | Q67: 0 | R67: 0 | Y67: 100000 | AA67: 473333 | AB67: 387500 | AF67: 387500 | AH67: 4643212 | AI67: 414583 | AJ67: 0 | AK67: 257505 | AL67: 0 | AM67: 22609 | AN67: 121212 | AO67: 0 | AW67: 815909 | AX67: 3827303 | AY67: =VLOOKUP(A67,'Hoja 1'!A:AX,50,0)-AX67 -> 0
A68: 17.754.059-5 | B68: F1 | C68: Schalchli | D68: Robinson | E68: Cristian Andres | F68: Ingeniero Gestión Integral Contratos (EGIC) | G68: OUTSOURCING, Salar Blanco, Salar Blanco | H68: 100 | I68: 30 | J68: 42 | K68: 0 | L68: 3161565 | M68: 3161565 | N68: 2942450 | O68: 219115 | P68: 0 | Q68: 0 | R68: 0 | AH68: 3161565 | AI68: 330700 | AJ68: 0 | AK68: 221310 | AL68: 0 | AM68: 0 | AN68: 84095 | AO68: 0 | AW68: 636105 | AX68: 2525460 | AY68: =VLOOKUP(A68,'Hoja 1'!A:AX,50,0)-AX68 -> 0
A69: 19.685.657-9 | B69: F1 | C69: Staeding | D69: Del Río | E69: Cristhian Nicolás | F69: Especialista de Medio Ambiente | G69: OUTSOURCING, Salar Blanco, Salar Blanco | H69: 100 | I69: 30 | J69: 60 | K69: 0 | L69: 3678639 | M69: 3778030 | N69: 3558915 | O69: 219115 | P69: 0 | Q69: 0 | R69: 0 | AH69: 3778030 | AI69: 384786 | AJ69: 0 | AK69: 257505 | AL69: 0 | AM69: 22668 | AN69: 124376 | AO69: 0 | AW69: 789335 | AX69: 2988695 | AY69: =VLOOKUP(A69,'Hoja 1'!A:AX,50,0)-AX69 -> 0
A70: 16.203.337-9 | B70: F1 | C70: Torreblanca | D70: Oyanedel | E70: Juan Pablo | F70: Administrador de Contrato | G70: OUTSOURCING, CODELCO, Modulo 2 | I70: 30 | J70: 42 | K70: 0 | L70: 2853558 | M70: 2853558 | N70: 2634443 | O70: 219115 | P70: 0 | Q70: 0 | R70: 0 | Y70: 100000 | AB70: 325000 | AF70: 325000 | AH70: 3603558 | AI70: 326447 | AJ70: 0 | AK70: 199749 | AL70: 0 | AM70: 17121 | AN70: 60150 | AO70: 0 | AP70: 250000 | AS70: 186501 | AV70: 17972 | AW70: 1057940 | AX70: 2545618 | AY70: =VLOOKUP(A70,'Hoja 1'!A:AX,50,0)-AX70 -> 0
A71: 16.513.123-1 | B71: F1 | C71: Torres | D71: Perez | E71: Gonzalo Andres | F71: Ingeniero Proyectos | G71: OUTSOURCING, Enap, Enap | H71: 100 | I71: 30 | J71: 37 | K71: 0 | L71: 2501208 | M71: 2501208 | N71: 2282093 | O71: 219115 | P71: 0 | Q71: 0 | R71: 0 | AB71: 250000 | AF71: 250000 | AH71: 3001208 | AI71: 264628 | AJ71: 0 | AK71: 175085 | AL71: 0 | AM71: 15007 | AN71: 43169 | AO71: 0 | AV71: 20667 | AW71: 518556 | AX71: 2482652 | AY71: =VLOOKUP(A71,'Hoja 1'!A:AX,50,0)-AX71 -> 0
A72: 16.403.006-7 | B72: F1 | C72: Trujillo | D72: Carrasco | E72: Joanett Angelica | F72: Risk Prevention Advisor | G72: OUTSOURCING, Endress Hauser, Endress Hauser | H72: 100 | I72: 29 | J72: 42 | K72: 0 | L72: 3235971 | M72: 3235971 | N72: 3016856 | O72: 219115 | P72: 0 | Q72: 0 | R72: 0 | AH72: 3235971 | AI72: 364694 | AJ72: 0 | AK72: 226518 | AL72: 0 | AM72: 19416 | AN72: 85358 | AO72: 0 | AW72: 695986 | AX72: 2539985 | AY72: =VLOOKUP(A72,'Hoja 1'!A:AX,50,0)-AX72 -> 0
A73: 17.155.741-0 | B73: F1 | C73: Valdivia | D73: Contreras | E73: Paulo Matías | F73: Gestor de Costos y Presupuestos | G73: OUTSOURCING, Enap, Enap | H73: 100 | I73: 30 | J73: 36 | K73: 0 | L73: 2399470 | M73: 2399470 | N73: 2180355 | O73: 219115 | P73: 0 | Q73: 0 | R73: 0 | AB73: 240000 | AF73: 240000 | AH73: 2879470 | AI73: 274499 | AJ73: 0 | AK73: 167963 | AL73: 0 | AM73: 0 | AN73: 39590 | AO73: 0 | AP73: 250000 | AW73: 732052 | AX73: 2147418 | AY73: =VLOOKUP(A73,'Hoja 1'!A:AX,50,0)-AX73 -> 250000
A74: 13.884.122-7 | B74: F1 | C74: Verdugo | D74: Ortiz | E74: Alvaro Eduardo | F74: Operador Tecnológico | G74: OUTSOURCING, Goldfields, Goldfield | H74: 100 | I74: 30 | J74: 40 | K74: 0 | L74: 3198955 | M74: 3198955 | N74: 2979840 | O74: 219115 | P74: 0 | Q74: 0 | R74: 0 | AH74: 3198955 | AI74: 365960 | AJ74: 0 | AK74: 223927 | AL74: 0 | AM74: 19194 | AN74: 82521 | AO74: 0 | AS74: 533720 | AW74: 1225322 | AX74: 1973633 | AY74: =VLOOKUP(A74,'Hoja 1'!A:AX,50,0)-AX74 -> 0
AX76: =SUM(AX7:AX74) -> 165417013

Sheet Hoja 1
A1: Libro: Remuneraciones
A2: Empresa: Grupo Avanza SPA (76.008.458-1)
A3: Periodo: Agosto 2026
A4: Fecha Generación: 24/08/2026 a las 07:59PM
A6: RUT | B6: CÓDIGO | C6: AP PATERNO | D6: AP MATERNO | E6: NOMBRES | F6: CARGO | G6: AREA | H6: CENTRO COSTO | I6: DÍAS TRABAJADOS | J6: HORAS SEMANALES | K6: HORAS NO TRABAJADAS | L6: BASE IMP. PREVISIÓN | M6: BASE IMP. CESANTÍA | N6: SUELDO BASE | O6: GRATIFICACIÓN | P6: APORTE ASISTENCIA | Q6: HORAS EXTRAS | R6: ASIGNACIÓN FAMILIAR | S6: ASIGNACIÓN POR TELETRABAJO | T6: ASIGNACIÓN SALA CUNA | U6: ASIGNACIÓN TELEFONÍA E INTERNET | V6: BONO | W6: BONO ESTUDIO | X6: BONO GESTIÓN | Y6: BONO INTERNET | Z6: BONO TELEFONIA | AA6: BONO TRIMESTRAL ACUERDO MARCO | AB6: COLACIÓN | AC6: COMISIONES | AD6: DIFERENCIA BONO | AE6: INCENTIVO TRIMESTRAL CUOTA 3 | AF6: MOVILIZACIÓN | AG6: VIATICO | AH6: TOTAL HABERES | AI6: PREVIS | AJ6: APV | AK6: SALUD | AL6: SALUD VOLUNTARIA | AM6: CESANTÍA | AN6: IMPUESTO | AO6: CUENTA_2 | AP6: ANTICIPO DE REMUNERACIONES | AQ6: CONVENIO FALP | AR6: CUENTA 2 PESOS | AS6: CRÉDITO PERSONAL CAJA LOS ANDES | AT6: PRESTAMO EMPRESA | AU6: PRÉSTAMO EMPRESA | AV6: SEGURO DE VIDA CAJA LOS ANDES | AW6: TOTAL DESCUENTOS | AX6: SUELDO LÍQUIDO | AY6: SOBREGIRO
A7: 16.280.871-0 | B7: F1 | C7: Aguirre | D7: Vásquez | E7: Stefania Alejandra | F7: Coordinador Senior de Cultura y Desarrollo | G7: OUTSOURCING, Codelco Casa Matriz, Codelco Casa Matriz | I7: 30 | J7: 40 | K7: 0 | L7: 2489778 | M7: 2489778 | N7: 1797330 | O7: 219115 | P7: 0 | Q7: 0 | R7: 0 | Y7: 30000 | AA7: 473333 | AB7: 130000 | AF7: 100000 | AH7: 2749778 | AI7: 280598 | AJ7: 0 | AK7: 174284 | AL7: 0 | AM7: 14939 | AN7: 42108 | AO7: 0 | AW7: 511929 | AX7: 2237849 | AY7: 0
A8: 17.858.538-k | B8: F1 | C8: Alucema | D8: Moraga | E8: Lucía Beatriz | F8: PSICOLOGA | G8: OUTSOURCING, Cia. Minera del Pacifico S.A., Cia. Minera del Pacifico S.A. | H8: 100 | I8: 0 | J8: 40 | K8: 0 | L8: 0 | M8: 0 | N8: 0 | O8: 0 | P8: 0 | Q8: 0 | R8: 0 | AB8: 0 | AF8: 0 | AH8: 0 | AI8: 0 | AJ8: 0 | AK8: 0 | AL8: 0 | AM8: 0 | AN8: 0 | AO8: 0 | AW8: 0 | AX8: 0 | AY8: 0
A9: 20.231.495-3 | B9: F1 | C9: Aravena | D9: Rodriguez | E9: Claudia Valentina | F9: Coordinador de Cultura y Desarrollo | G9: OUTSOURCING, Codelco Casa Matriz, Codelco Casa Matriz | I9: 30 | J9: 40 | K9: 0 | L9: 2002961 | M9: 2002961 | N9: 1310513 | O9: 219115 | P9: 0 | Q9: 0 | R9: 0 | Y9: 75000 | AA9: 473333 | AB9: 150000 | AF9: 75000 | AH9: 2302961 | AI9: 209510 | AJ9: 5000 | AK9: 140207 | AL9: 0 | AM9: 12018 | AN9: 26959 | AO9: 0 | AR9: 65000 | AW9: 458694 | AX9: 1844267 | AY9: 0
A10: 18.354.198-6 | B10: F1 | C10: Araya | D10: Cortés | E10: Eduardo Antonio | F10: Programador | G10: Over Head, IT, IT | H10: 100 | I10: 30 | J10: 42 | K10: 0 | L10: 1025146 | M10: 1025146 | N10: 820117 | O10: 205029 | P10: 0 | Q10: 0 | R10: 0 | AB10: 90000 | AF10: 90000 | AH10: 1205146 | AI10: 108460 | AJ10: 0 | AK10: 71760 | AL10: 0 | AM10: 6151 | AN10: 0 | AO10: 0 | AW10: 186371 | AX10: 1018775 | AY10: 0
A11: 14.027.919-6 | B11: F1 | C11: Bawarshi | D11: Abarzua | E11: Alfonso Ignacio | F11: Director Ejecutivo | G11: Over Head, Administración, Comercial | H11: 1111 | I11: 30 | J11: 44 | K11: 0 | L11: 3678639 | M11: 5526134 | N11: 12365703 | O11: 219115 | P11: 0 | Q11: 0 | R11: 0 | AH11: 12584818 | AI11: 420836 | AJ11: 0 | AK11: 257505 | AL11: 125278 | AM11: 0 | AN11: 2496412 | AO11: 0 | AW11: 3300031 | AX11: 9284787 | AY11: 0
A12: 17.408.142-5 | B12: F1 | C12: Bawarshi | D12: Abarzua | E12: Gabriela Estefania | F12: Analista Senior DO | G12: Over Head, Administración, Comercial | H12: 1111 | I12: 30 | J12: 42 | K12: 0 | L12: 861875 | M12: 861875 | N12: 689500 | O12: 172375 | P12: 0 | Q12: 0 | R12: 0 | AH12: 861875 | AI12: 96185 | AJ12: 0 | AK12: 60331 | AL12: 156136 | AM12: 5171 | AN12: 0 | AO12: 0 | AW12: 317823 | AX12: 544052 | AY12: 0
A13: 22.074.650-k | B13: F1 | C13: Bustiman | D13: Gonzalez | E13: Gabriel Bastian | F13: Technician Service Assistance | G13: OUTSOURCING, Endress Hauser, Endress Hauser | H13: 100 | I13: 30 | J13: 44 | K13: 0 | L13: 800000 | M13: 800000 | N13: 640000 | O13: 160000 | P13: 0 | Q13: 0 | R13: 0 | AH13: 800000 | AI13: 83680 | AJ13: 0 | AK13: 56000 | AL13: 0 | AM13: 4800 | AN13: 0 | AO13: 0 | AW13: 144480 | AX13: 655520 | AY13: 0
A14: 28.830.860-8 | B14: F1 | C14: Camacho | D14: Cordero | E14: Roger Alberto | F14: Gestor de Procesos | G14: OUTSOURCING, Goldfields, Goldfield | H14: 100 | I14: 30 | J14: 40 | K14: 0 | L14: 2500533 | M14: 2500533 | N14: 2281418 | O14: 219115 | P14: 0 | Q14: 0 | R14: 0 | AH14: 2500533 | AI14: 261556 | AJ14: 0 | AK14: 175037 | AL14: 55328 | AM14: 0 | AN14: 41654 | AO14: 0 | AW14: 533575 | AX14: 1966958 | AY14: 0
A15: 20.043.827-2 | B15: F1 | C15: Cantarero | D15: Pacheco | E15: Elias Matias Ignacio | F15: SERVICE TECHNICIAL | G15: OUTSOURCING, Endress Hauser, Endress Hauser | H15: 100 | I15: 30 | J15: 42 | K15: 0 | L15: 1356403 | M15: 1356403 | N15: 1137288 | O15: 219115 | P15: 0 | Q15: 0 | R15: 0 | AH15: 1356403 | AI15: 143507 | AJ15: 0 | AK15: 94948 | AL15: 0 | AM15: 8138 | AN15: 5702 | AO15: 0 | AW15: 252295 | AX15: 1104108 | AY15: 0
A16: 20.411.355-6 | B16: F1 | C16: Carreño | D16: Espinoza | E16: Amaranta Paola | F16: Asistente de Gestion de Personas | G16: OUTSOURCING, Cia. Minera del Pacifico S.A., Cia. Minera del Pacifico S.A. | H16: 100 | I16: 29 | J16: 40 | K16: 0 | L16: 1283580 | M16: 1283580 | N16: 1064465 | O16: 219115 | P16: 0 | Q16: 0 | R16: 0 | AB16: 43500 | AF16: 43500 | AH16: 1370580 | AI16: 135803 | AJ16: 0 | AK16: 89851 | AL16: 0 | AM16: 7701 | AN16: 3319 | AO16: 0 | AW16: 236674 | AX16: 1133906 | AY16: 0
A17: 21.380.747-1 | B17: F1 | C17: Catalan | D17: Mardones | E17: Javiera Alejandra | F17: Asistente Contable | G17: OUTSOURCING, CONTINENTAL SEGUROS, CONTINENTAL SEGUROS | H17: 100 | I17: 30 | J17: 42 | K17: 0 | L17: 847959 | M17: 847959 | N17: 678367 | O17: 169592 | P17: 0 | Q17: 0 | R17: 0 | AB17: 90000 | AF17: 90000 | AH17: 1027959 | AI17: 89714 | AJ17: 0 | AK17: 59357 | AL17: 0 | AM17: 5088 | AN17: 0 | AO17: 0 | AW17: 154159 | AX17: 873800 | AY17: 0
A18: 19.135.138-k | B18: F1 | C18: Cataldo | D18: Caviedes | E18: Claudia Fernanda | F18: Coordinador de Reclutamiento y Selección | G18: Hunting, Hunting, Hunting | H18: 1111 | I18: 30 | J18: 42 | K18: 0 | L18: 1758961 | M18: 1758961 | N18: 1539846 | O18: 219115 | P18: 0 | Q18: 0 | R18: 0 | AB18: 100000 | AF18: 100000 | AH18: 1958961 | AI18: 186098 | AJ18: 0 | AK18: 123127 | AL18: 1865 | AM18: 10554 | AN18: 18802 | AO18: 0 | AQ18: 19800 | AW18: 360246 | AX18: 1598715 | AY18: 0
A19: 19.867.384-6 | B19: F1 | C19: Caul | D19: Cortes | E19: Francisca Valentina | F19: Coordinador Avanzado | G19: OUTSOURCING, CODELCO CHILE -V. P., CODELCO CHILE -V. P. | H19: 100 | I19: 30 | J19: 40 | K19: 0 | L19: 2018709 | M19: 2018709 | N19: 1484039 | O19: 219115 | P19: 0 | Q19: 0 | R19: 0 | AB19: 100000 | AE19: 315555 | AF19: 100000 | AH19: 2218709 | AI19: 213579 | AJ19: 0 | AK19: 141310 | AL19: 0 | AM19: 12112 | AN19: 27378 | AO19: 0 | AW19: 394379 | AX19: 1824330 | AY19: 0
A20: 16.479.434-2 | B20: F1 | C20: Correa | D20: Araya | E20: Camila Denis | F20: KEY ACCOUNT MANAGER SENIOR | G20: Over Head, Administración, Comercial | H20: 1111 | I20: 30 | J20: 42 | K20: 0 | L20: 2071498 | M20: 2071498 | N20: 1852383 | O20: 219115 | P20: 0 | Q20: 0 | R20: 0 | AB20: 80000 | AF20: 80000 | AH20: 2231498 | AI20: 233458 | AJ20: 0 | AK20: 145005 | AL20: 42933 | AM20: 12429 | AN20: 26816 | AO20: 0 | AW20: 460641 | AX20: 1770857 | AY20: 0
A21: 26.972.625-3 | B21: F1 | C21: De Sousa | D21: Garcia | E21: Stephen William | F21: Control Interno | G21: OUTSOURCING, Goldfields, Goldfield | H21: 100 | I21: 30 | J21: 42 | K21: 0 | L21: 2279115 | M21: 2279115 | N21: 2060000 | O21: 219115 | P21: 0 | Q21: 0 | R21: 0 | AB21: 100000 | AF21: 100000 | AH21: 2479115 | AI21: 238395 | AJ21: 0 | AK21: 159538 | AL21: 89138 | AM21: 13675 | AN21: 32444 | AO21: 0 | AP21: 100000 | AW21: 633190 | AX21: 1845925 | AY21: 0
A22: 26.304.359-6 | B22: F1 | C22: Diaz | D22: Gonzalez | E22: Fatima | F22: Supervisor Técnico del Servicio | G22: OUTSOURCING, Enap, Enap | H22: 100 | I22: 30 | J22: 37 | K22: 0 | L22: 2816897 | M22: 2816897 | N22: 2597782 | O22: 219115 | P22: 0 | Q22: 0 | R22: 0 | AB22: 280000 | AF22: 280000 | AH22: 3376897 | AI22: 314366 | AJ22: 0 | AK22: 197183 | AL22: 37473 | AM22: 16901 | AN22: 55409 | AO22: 0 | AW22: 621332 | AX22: 2755565 | AY22: 0
A23: 17.318.383-6 | B23: F1 | C23: Espinoza | D23: Latorre | E23: Daniela Paz Loreto | F23: Especialista en Biodiversidad | G23: OUTSOURCING, Salar Blanco, Salar Blanco | H23: 100 | I23: 22 | J23: 42 | K23: 0 | L23: 3581244 | M23: 3581244 | N23: 3362129 | O23: 219115 | P23: 0 | Q23: 0 | R23: 0 | AH23: 3581244 | AI23: 409694 | AJ23: 0 | AK23: 250687 | AL23: 0 | AM23: 21487 | AN23: 107281 | AO23: 0 | AW23: 789149 | AX23: 2792095 | AY23: 0
A24: 25.387.977-7 | B24: F1 | C24: Fuentes | D24: Rodriguez | E24: Levy Johan | F24: Especialista Modelamiento | G24: OUTSOURCING, Salar Blanco, Salar Blanco | H24: 100 | I24: 30 | J24: 42 | K24: 0 | L24: 3678639 | M24: 5273749 | N24: 4958453 | O24: 219115 | P24: 0 | Q24: 0 | R24: 0 | AD24: 96181 | AH24: 5273749 | AI24: 420836 | AJ24: 0 | AK24: 257505 | AL24: 74063 | AM24: 0 | AN24: 298676 | AO24: 0 | AW24: 1051080 | AX24: 4222669 | AY24: 0
A25: 18.585.098-6 | B25: F1 | C25: Garcia | D25: Cruz | E25: Isabel Ivania | F25: Coordinador Senior | G25: OUTSOURCING, CODELCO CHILE -V. P., CODELCO CHILE -V. P. | H25: 100 | I25: 30 | J25: 40 | K25: 0 | L25: 3678639 | M25: 3696162 | N25: 3003714 | O25: 219115 | P25: 0 | Q25: 0 | R25: 0 | AB25: 100000 | AE25: 473333 | AF25: 100000 | AH25: 3896162 | AI25: 414583 | AJ25: 0 | AK25: 257505 | AL25: 0 | AM25: 22177 | AN25: 115482 | AO25: 0 | AQ25: 19800 | AW25: 829547 | AX25: 3066615 | AY25: 0
A26: 21.166.392-8 | B26: F1 | C26: Garcia | D26: Soria | E26: Alexis Joshua | F26: Especialista en Sistemas | G26: OUTSOURCING, Enap, Enap | H26: 100 | I26: 30 | J26: 37 | K26: 0 | L26: 2399470 | M26: 2399470 | N26: 2180355 | O26: 219115 | P26: 0 | Q26: 0 | R26: 0 | AB26: 250000 | AF26: 250000 | AH26: 2899470 | AI26: 250985 | AJ26: 0 | AK26: 167963 | AL26: 0 | AM26: 14397 | AN26: 39955 | AO26: 0 | AW26: 473300 | AX26: 2426170 | AY26: 0
A27: 17.852.693-6 | B27: F1 | C27: Gil | D27: Salazar | E27: Ivan Ignacio | F27: SERVICE TECHNICIAL | G27: OUTSOURCING, Endress Hauser, Endress Hauser | H27: 100 | I27: 30 | J27: 42 | K27: 0 | L27: 1356403 | M27: 1356403 | N27: 1137288 | O27: 219115 | P27: 0 | Q27: 0 | R27: 0 | AH27: 1356403 | AI27: 143507 | AJ27: 0 | AK27: 94948 | AL27: 0 | AM27: 8138 | AN27: 5702 | AO27: 0 | AW27: 252295 | AX27: 1104108 | AY27: 0
A28: 18.668.865-1 | B28: F1 | C28: Gomez | D28: Paris | E28: Rodrigo Ignacio | F28: Coordinador Senior de Cultura y Desarrollo | G28: OUTSOURCING, Codelco Casa Matriz, Codelco Casa Matriz | I28: 30 | J28: 40 | K28: 0 | L28: 2534485 | M28: 2534485 | N28: 1684259 | O28: 219115 | P28: 0 | Q28: 0 | R28: 0 | Y28: 30000 | AA28: 631111 | AB28: 170000 | AF28: 170000 | AH28: 2904485 | AI28: 268149 | AJ28: 0 | AK28: 177414 | AL28: 0 | AM28: 15207 | AN28: 44258 | AO28: 0 | AW28: 505028 | AX28: 2399457 | AY28: 0
A29: 15.934.450-9 | B29: F1 | C29: Gonzalez | D29: Muñoz | E29: Viviana Soledad | F29: Gerente Comercial | G29: Over Head, Administración, Comercial | H29: 1111 | I29: 30 | J29: 44 | K29: 0 | L29: 3678639 | M29: 3953939 | N29: 3734824 | O29: 219115 | P29: 0 | Q29: 0 | R29: 0 | T29: 600000 | AB29: 200000 | AF29: 200000 | AH29: 4953939 | AI29: 420836 | AJ29: 0 | AK29: 257505 | AL29: 129079 | AM29: 23724 | AN29: 135481 | AO29: 0 | AQ29: 19800 | AW29: 986425 | AX29: 3967514 | AY29: 0
A30: 19.928.652-8 | B30: F1 | C30: Guerrero | D30: Maldonado | E30: Geraldine | F30: Coordinadora Avanzada | G30: OUTSOURCING, CODELCO CHILE -V. P., CODELCO CHILE -V. P. | H30: 100 | I30: 30 | J30: 40 | K30: 0 | L30: 2176352 | M30: 2176352 | N30: 1483904 | O30: 219115 | P30: 0 | Q30: 0 | R30: 0 | AB30: 100000 | AE30: 473333 | AF30: 100000 | AH30: 2376352 | AI30: 227646 | AJ30: 0 | AK30: 152345 | AL30: 0 | AM30: 13058 | AN30: 32642 | AO30: 0 | AW30: 425691 | AX30: 1950661 | AY30: 0
A31: 16.477.999-8 | B31: F1 | C31: Gutiérrez | D31: Castro | E31: Carolina Arlette | F31: Analista de Logística JR | G31: OUTSOURCING, Tesa Tape Chile S.A., Tesa Tape Chile S.A. | H31: 100 | I31: 30 | J31: 42 | K31: 0 | L31: 1596165 | M31: 1596165 | N31: 1358500 | O31: 219115 | P31: 0 | Q31: 0 | R31: 0 | V31: 18550 | AH31: 1596165 | AI31: 182601 | AJ31: 0 | AK31: 111732 | AL31: 0 | AM31: 9577 | AN31: 13000 | AO31: 0 | AW31: 316910 | AX31: 1279255 | AY31: 0
A32: 15.737.550-4 | B32: F1 | C32: Hurtado | D32: Canto | E32: Alejandro Eduardo | F32: Coordinador Senior | G32: OUTSOURCING, CODELCO CHILE -V. P., CODELCO CHILE -V. P. | H32: 100 | I32: 30 | J32: 42 | K32: 0 | L32: 3351652 | M32: 3351652 | N32: 2816982 | O32: 219115 | P32: 0 | Q32: 0 | R32: 0 | AB32: 100000 | AE32: 315555 | AF32: 100000 | AH32: 3551652 | AI32: 377731 | AJ32: 0 | AK32: 234616 | AL32: 16921 | AM32: 20110 | AN32: 91513 | AO32: 0 | AS32: 385837 | AW32: 1126728 | AX32: 2424924 | AY32: 0
A33: 18.467.232-4 | B33: F1 | C33: Jamis | D33: Matus | E33: Juan Ignacio | F33: Gerente de Clientes y Licitaciones | G33: Over Head, Administración, Comercial | H33: 1111 | I33: 30 | J33: 44 | K33: 0 | L33: 2860189 | M33: 2860189 | N33: 2641074 | O33: 219115 | P33: 0 | Q33: 0 | R33: 0 | AB33: 150000 | AF33: 150000 | AH33: 3160189 | AI33: 302608 | AJ33: 0 | AK33: 200213 | AL33: 0 | AM33: 17161 | AN33: 62547 | AO33: 0 | AQ33: 19800 | AW33: 602329 | AX33: 2557860 | AY33: 0
A34: 15.805.887-1 | B34: F1 | C34: Jara | D34: Ochoa | E34: Jacqueline Carolina | F34: Asesor Senior de Prevención de Riesgos | G34: OUTSOURCING, CODELCO, Modulo 2 | I34: 30 | J34: 42 | K34: 0 | L34: 2748807 | M34: 2748807 | N34: 2056359 | O34: 219115 | P34: 0 | Q34: 0 | R34: 0 | Y34: 125000 | AA34: 473333 | AB34: 250000 | AF34: 250000 | AH34: 3373807 | AI34: 309791 | AJ34: 0 | AK34: 192416 | AL34: 1080 | AM34: 16493 | AN34: 53653 | AO34: 0 | AS34: 186081 | AW34: 759514 | AX34: 2614293 | AY34: 0
A35: 13.462.122-2 | B35: F1 | C35: Labraña | D35: Gutierrez | E35: Maria Carolina | F35: Coordinador Experto | G35: OUTSOURCING, CODELCO CHILE -V. P., CODELCO CHILE -V. P. | H35: 100 | I35: 30 | J35: 42 | K35: 0 | L35: 3678639 | M35: 4263081 | N35: 3570633 | O35: 219115 | P35: 0 | Q35: 0 | R35: 0 | AB35: 100000 | AE35: 473333 | AF35: 100000 | AH35: 4463081 | AI35: 414583 | AJ35: 0 | AK35: 257505 | AL35: 1471 | AM35: 25578 | AN35: 160564 | AO35: 0 | AS35: 29854 | AW35: 889555 | AX35: 3573526 | AY35: 0
A36: 13.035.195-6 | B36: F1 | C36: La Roche | D36: Benitez | E36: Udo Franz | F36: ASSET OPTIMIZATION | G36: OUTSOURCING, Goldfields, Goldfield | H36: 100 | I36: 30 | J36: 40 | K36: 0 | L36: 3678639 | M36: 4328779 | N36: 4109664 | O36: 219115 | P36: 0 | Q36: 0 | R36: 0 | AH36: 4328779 | AI36: 414583 | AJ36: 0 | AK36: 257505 | AL36: 306471 | AM36: 25973 | AN36: 168443 | AO36: 0 | AW36: 1172975 | AX36: 3155804 | AY36: 0
A37: 20.465.683-5 | B37: F1 | C37: Morales | D37: Valdes | E37: Barbara Jesus | F37: Marketing Analyst | G37: OUTSOURCING, EDGEWELL CHILE, EDGEWELL CHILE | H37: 100 | I37: 21 | J37: 40 | K37: 0 | L37: 1615615 | M37: 1615615 | N37: 1396500 | O37: 219115 | P37: 0 | Q37: 0 | R37: 0 | S37: 7000 | U37: 14000 | AH37: 1636615 | AI37: 170932 | AJ37: 0 | AK37: 113093 | AL37: 21839 | AM37: 9694 | AN37: 13312 | AO37: 0 | AW37: 328870 | AX37: 1307745 | AY37: 0
A38: 16.163.207-4 | B38: F1 | C38: Morrison | D38: Robles | E38: Dawn Faye | F38: Asistente Comercial Bilingue | G38: Over Head, Administración, Comercial | H38: 1111 | I38: 30 | J38: 44 | K38: 0 | L38: 2586937 | M38: 2586937 | N38: 2367822 | O38: 219115 | P38: 0 | Q38: 0 | R38: 0 | AH38: 2586937 | AI38: 288702 | AJ38: 0 | AK38: 181086 | AL38: 408028 | AM38: 15522 | AN38: 42318 | AO38: 0 | AW38: 935656 | AX38: 1651281 | AY38: 0
A39: 15.475.910-7 | B39: F1 | C39: Muñoz | D39: Gonzalez | E39: Jocelyn Andrea | F39: Receptionist & Administrative Assistant | G39: OUTSOURCING, Endress Hauser, Endress Hauser | H39: 100 | I39: 3 | J39: 40 | K39: 0 | L39: 183941 | M39: 183941 | N39: 147153 | O39: 36788 | P39: 0 | Q39: 0 | R39: 0 | AH39: 183941 | AI39: 21043 | AJ39: 0 | AK39: 12876 | AL39: 0 | AM39: 1104 | AN39: 0 | AO39: 0 | AQ39: 29700 | AW39: 64723 | AX39: 119218 | AY39: 0
A40: 18.057.004-7 | B40: F1 | C40: Muñoz | D40: Matamala | E40: Denisse Ninoska | F40: SERVICE ASSISTANT | G40: OUTSOURCING, Endress Hauser, Endress Hauser | H40: 100 | I40: 30 | J40: 42 | K40: 0 | L40: 1700761 | M40: 1700761 | N40: 1481646 | O40: 219115 | P40: 0 | Q40: 0 | R40: 0 | AH40: 1700761 | AI40: 179941 | AJ40: 0 | AK40: 119053 | AL40: 0 | AM40: 10205 | AN40: 16972 | AO40: 0 | AW40: 326171 | AX40: 1374590 | AY40: 0
A41: 20.047.644-1 | B41: F1 | C41: Muñoz | D41: Muñoz | E41: Hernán Stefano | F41: Jefe de Administración y Control de Gestión | G41: Over Head, Administración, Comercial | H41: 1111 | I41: 30 | J41: 42 | K41: 0 | L41: 1235115 | M41: 1235115 | N41: 1016000 | O41: 219115 | P41: 0 | Q41: 0 | R41: 0 | Y41: 15000 | AB41: 50000 | AF41: 50000 | AH41: 1350115 | AI41: 129193 | AJ41: 0 | AK41: 86458 | AL41: 0 | AM41: 7411 | AN41: 1792 | AO41: 0 | AS41: 74207 | AU41: 50000 | AW41: 349061 | AX41: 1001054 | AY41: 0
A42: 18.445.816-0 | B42: F1 | C42: Muñoz | D42: Pardo | E42: Sebastian Andres | F42: Ingeniero Senior | G42: OUTSOURCING, CODELCO, Modulo 2 | I42: 30 | J42: 42 | K42: 0 | L42: 3678639 | M42: 3768212 | N42: 3075764 | O42: 219115 | P42: 0 | Q42: 0 | R42: 0 | Y42: 100000 | AA42: 473333 | AB42: 387500 | AF42: 387500 | AH42: 4643212 | AI42: 389200 | AJ42: 0 | AK42: 257505 | AL42: 0 | AM42: 22609 | AN42: 123243 | AO42: 0 | AW42: 792557 | AX42: 3850655 | AY42: 0
A43: 21.081.959-2 | B43: F1 | C43: Muñoz | D43: Parra | E43: Martín Alejandro | F43: Responsable de RRHH y Apoyo en Control de Gestión | G43: Over Head, Administración, Comercial | H43: 1111 | I43: 30 | J43: 41 | K43: 0 | L43: 714199 | M43: 714199 | N43: 571359 | O43: 142840 | P43: 0 | Q43: 0 | R43: 0 | Y43: 15000 | AB43: 50000 | AF43: 50000 | AH43: 829199 | AI43: 74705 | AJ43: 0 | AK43: 49994 | AL43: 0 | AM43: 4285 | AN43: 0 | AO43: 0 | AW43: 128984 | AX43: 700215 | AY43: 0
A44: 16.642.221-3 | B44: F1 | C44: Muñoz | D44: Vasquez | E44: Camila Yanara | F44: Consultor Senior de Desarrollo | G44: OUTSOURCING, Codelco Casa Matriz, Codelco Casa Matriz | I44: 30 | J44: 40 | K44: 0 | L44: 3047082 | M44: 3047082 | N44: 2354634 | O44: 219115 | P44: 0 | Q44: 0 | R44: 0 | Y44: 35000 | AA44: 473333 | AB44: 250000 | AF44: 215000 | AH44: 3547082 | AI44: 343406 | AJ44: 0 | AK44: 213296 | AL44: 0 | AM44: 18282 | AN44: 73099 | AO44: 0 | AW44: 648083 | AX44: 2898999 | AY44: 0
A45: 15.310.116-7 | B45: F1 | C45: Narea | D45: Biscupovich | E45: Maria Paz | F45: CONSULTOR SENIOR | G45: OUTSOURCING, Codelco Casa Matriz, Codelco Casa Matriz | I45: 30 | J45: 40 | K45: 0 | L45: 3654524 | M45: 3654524 | N45: 2804298 | O45: 219115 | P45: 0 | Q45: 0 | R45: 0 | Y45: 35000 | AA45: 631111 | AB45: 290000 | AF45: 255000 | AH45: 4234524 | AI45: 411865 | AJ45: 0 | AK45: 255817 | AL45: 0 | AM45: 21927 | AN45: 112524 | AO45: 0 | AW45: 802133 | AX45: 3432391 | AY45: 0
A46: 13.792.103-0 | B46: F1 | C46: Neira | D46: Molina | E46: Leonardo David | F46: Ingeniero Proyectos | G46: OUTSOURCING, Enap, Enap | H46: 100 | I46: 30 | J46: 37 | K46: 0 | L46: 2501208 | M46: 2501208 | N46: 2282093 | O46: 219115 | P46: 0 | Q46: 0 | R46: 0 | AB46: 250000 | AF46: 250000 | AH46: 3001208 | AI46: 281886 | AJ46: 0 | AK46: 175085 | AL46: 0 | AM46: 15007 | AN46: 42479 | AO46: 0 | AW46: 514457 | AX46: 2486751 | AY46: 0
A47: 19.983.000-7 | B47: F1 | C47: Nuñez | D47: Gonzales | E47: Pablo Ignacio | F47: Analista Supply Planning | G47: OUTSOURCING, Tesa Tape Chile S.A., Tesa Tape Chile S.A. | H47: 100 | I47: 12 | J47: 40 | K47: 0 | L47: 724670 | M47: 724670 | N47: 579736 | O47: 144934 | P47: 0 | Q47: 0 | R47: 0 | AH47: 724670 | AI47: 82975 | AJ47: 0 | AK47: 50727 | AL47: 0 | AM47: 0 | AN47: 0 | AO47: 0 | AW47: 133702 | AX47: 590968 | AY47: 0
A48: 18.300.849-8 | B48: F1 | C48: Nuñez | D48: Vazquez | E48: Giselle Andrea | F48: Asesor Senior de Prevención de Riesgos | G48: OUTSOURCING, CODELCO, Modulo 2 | I48: 30 | J48: 42 | K48: 0 | L48: 2748807 | M48: 2748807 | N48: 2056359 | O48: 219115 | P48: 0 | Q48: 0 | R48: 0 | Y48: 125000 | AA48: 473333 | AB48: 250000 | AF48: 250000 | AH48: 3373807 | AI48: 314464 | AJ48: 0 | AK48: 192416 | AL48: 0 | AM48: 16493 | AN48: 53365 | AO48: 0 | AW48: 576738 | AX48: 2797069 | AY48: 0
A49: 18.416.923-1 | B49: F1 | C49: Ojeda | D49: Islas | E49: Esteban Neftali | F49: Gestor Planificación y Control | G49: OUTSOURCING, Enap, Enap | H49: 100 | I49: 30 | J49: 37 | K49: 0 | L49: 2501208 | M49: 2501208 | N49: 2282093 | O49: 219115 | P49: 0 | Q49: 0 | R49: 0 | AB49: 250000 | AF49: 250000 | AH49: 3001208 | AI49: 264628 | AJ49: 0 | AK49: 175085 | AL49: 0 | AM49: 15007 | AN49: 43169 | AO49: 0 | AW49: 497889 | AX49: 2503319 | AY49: 0
A50: 15.084.306-5 | B50: F1 | C50: Orellana | D50: Gonzalez | E50: Gabriel Ivan | F50: Ingeniero Senior | G50: OUTSOURCING, CODELCO, Modulo 2 | I50: 30 | J50: 42 | K50: 0 | L50: 3678639 | M50: 3768212 | N50: 3075764 | O50: 219115 | P50: 0 | Q50: 0 | R50: 0 | Y50: 100000 | AA50: 473333 | AB50: 387500 | AF50: 387500 | AH50: 4643212 | AI50: 414583 | AJ50: 0 | AK50: 257505 | AL50: 0 | AM50: 22609 | AN50: 121212 | AO50: 0 | AS50: 11860 | AV50: 34187 | AW50: 861956 | AX50: 3781256 | AY50: 0
A51: 16.038.646-0 | B51: F1 | C51: Osorio | D51: Petersen | E51: Marcos Felipe | F51: Ingeniero Proyectos | G51: OUTSOURCING, Enap, Enap | H51: 100 | I51: 30 | J51: 37 | K51: 0 | L51: 2621208 | M51: 2621208 | N51: 2402093 | O51: 219115 | P51: 0 | Q51: 0 | R51: 0 | AB51: 190000 | AF51: 190000 | AH51: 3001208 | AI51: 277324 | AJ51: 0 | AK51: 183485 | AL51: 0 | AM51: 15727 | AN51: 47096 | AO51: 0 | AW51: 523632 | AX51: 2477576 | AY51: 0
A52: 17.392.078-4 | B52: F1 | C52: Pallauta | D52: Rossel | E52: Sergio Antonio | F52: Ingeniero Senior de Proyecto | G52: OUTSOURCING, CODELCO, Modulo 2 | I52: 30 | J52: 42 | K52: 0 | L52: 3678639 | M52: 3752909 | N52: 3060461 | O52: 219115 | P52: 0 | Q52: 0 | R52: 0 | Y52: 100000 | AA52: 473333 | AB52: 387500 | AF52: 387500 | AH52: 4627909 | AI52: 389200 | AJ52: 0 | AK52: 257505 | AL52: 0 | AM52: 22517 | AN52: 122026 | AO52: 0 | AW52: 791248 | AX52: 3836661 | AY52: 0
A53: 14.120.765-2 | B53: F1 | C53: Paredes | D53: Werth | E53: Macarena Paz | F53: Asistente Administrativa | G53: OUTSOURCING, EDGEWELL CHILE, EDGEWELL CHILE | H53: 100 | I53: 30 | J53: 42 | K53: 0 | L53: 1231897 | M53: 1231897 | N53: 1012782 | O53: 219115 | P53: 0 | Q53: 0 | R53: 0 | U53: 20000 | AH53: 1251897 | AI53: 141052 | AJ53: 0 | AK53: 86233 | AL53: 0 | AM53: 7391 | AN53: 1198 | AO53: 0 | AQ53: 19800 | AW53: 255674 | AX53: 996223 | AY53: 0
A54: 19.704.689-9 | B54: F1 | C54: Paz | D54: Martinez | E54: Camila Adriana | F54: Consultor Senior Desempeño | G54: OUTSOURCING, Codelco Casa Matriz, Codelco Casa Matriz | I54: 30 | J54: 40 | K54: 0 | L54: 3058855 | M54: 3058855 | N54: 2366407 | O54: 219115 | P54: 0 | Q54: 0 | R54: 0 | Y54: 35000 | AA54: 473333 | AB54: 250000 | AF54: 215000 | AH54: 3558855 | AI54: 319956 | AJ54: 0 | AK54: 214120 | AL54: 0 | AM54: 18353 | AN54: 75845 | AO54: 0 | AS54: 368400 | AW54: 996674 | AX54: 2562181 | AY54: 0
A55: 15.635.202-0 | B55: F1 | C55: Peña | D55: Ávalos | E55: Macarena Del Pilar | F55: PSICOLOGA | G55: OUTSOURCING, Cia. Minera del Pacifico S.A., Cia. Minera del Pacifico S.A. | H55: 100 | I55: 30 | J55: 40 | K55: 0 | L55: 2193260 | M55: 2193260 | N55: 1974145 | O55: 219115 | P55: 0 | Q55: 0 | R55: 0 | T55: 350000 | U55: 25000 | AB55: 165000 | AF55: 150000 | AH55: 2883260 | AI55: 250909 | AJ55: 0 | AK55: 153528 | AL55: 0 | AM55: 13160 | AN55: 32336 | AO55: 0 | AW55: 449933 | AX55: 2433327 | AY55: 0
A56: 12.693.080-1 | B56: F1 | C56: Perez | D56: Miranda | E56: Jose Antonio | F56: Ingeniero Senior | G56: OUTSOURCING, CODELCO, Modulo 2 | I56: 30 | J56: 42 | K56: 0 | L56: 3678639 | M56: 3768212 | N56: 3075764 | O56: 219115 | P56: 0 | Q56: 0 | R56: 0 | Y56: 100000 | AA56: 473333 | AB56: 387500 | AF56: 387500 | AH56: 4643212 | AI56: 414583 | AJ56: 0 | AK56: 257505 | AL56: 0 | AM56: 22609 | AN56: 121212 | AO56: 0 | AW56: 815909 | AX56: 3827303 | AY56: 0
A57: 22.335.317-7 | B57: F1 | C57: Pinto | D57: Guillen | E57: Carlos Enrique | F57: SUPERINTENDENTE DE CONTRATOS | G57: OUTSOURCING, Goldfields, Goldfield | H57: 100 | I57: 30 | J57: 40 | K57: 0 | L57: 3678639 | M57: 5526134 | N57: 5396846 | O57: 219115 | P57: 0 | Q57: 0 | R57: 0 | AH57: 5615961 | AI57: 414583 | AJ57: 0 | AK57: 257505 | AL57: 343585 | AM57: 33157 | AN57: 341243 | AO57: 0 | AW57: 1390073 | AX57: 4225888 | AY57: 0
A58: 16.822.048-0 | B58: F1 | C58: Quiroz | D58: Garcia | E58: Jose Miguel | F58: Especialista de Planificación | G58: OUTSOURCING, Salar Blanco, Salar Blanco | H58: 100 | I58: 30 | J58: 42 | K58: 0 | L58: 3678639 | M58: 3773058 | N58: 3553943 | O58: 219115 | P58: 0 | Q58: 0 | R58: 0 | AH58: 3773058 | AI58: 389200 | AJ58: 0 | AK58: 257505 | AL58: 0 | AM58: 0 | AN58: 125439 | AO58: 0 | AW58: 772144 | AX58: 3000914 | AY58: 0
A59: 10.112.634-k | B59: F1 | C59: Ramos | D59: Padilla | E59: Eusebio Hernan | F59: Gestor de Materiales | G59: OUTSOURCING, Enap, Enap | H59: 100 | I59: 30 | J59: 37 | K59: 0 | L59: 1687306 | M59: 1687306 | N59: 1468191 | O59: 219115 | P59: 0 | Q59: 0 | R59: 0 | AB59: 170000 | AF59: 170000 | AH59: 2027306 | AI59: 193028 | AJ59: 0 | AK59: 118111 | AL59: 0 | AM59: 10124 | AN59: 15951 | AO59: 0 | AW59: 337214 | AX59: 1690092 | AY59: 0
A60: 13.601.169-3 | B60: F1 | C60: Riquelme | D60: Riquelme | E60: José Alejandro | F60: Logistics Analyst & Customer Service | G60: OUTSOURCING, Tesa Tape Chile S.A., Tesa Tape Chile S.A. | H60: 100 | I60: 30 | J60: 42 | K60: 0 | L60: 2309115 | M60: 2309115 | N60: 2090000 | O60: 219115 | P60: 0 | Q60: 0 | R60: 0 | Y60: 18550 | AH60: 2327665 | AI60: 264394 | AJ60: 0 | AK60: 161638 | AL60: 100894 | AM60: 13855 | AN60: 32244 | AO60: 0 | AS60: 247037 | AW60: 820062 | AX60: 1507603 | AY60: 0
A61: 19.763.405-7 | B61: F1 | C61: Rivera | D61: Soto | E61: Sofia Elena | F61: CONSULTOR SENIOR | G61: OUTSOURCING, Codelco Casa Matriz, Codelco Casa Matriz | I61: 30 | J61: 40 | K61: 0 | L61: 3216633 | M61: 3216633 | N61: 2366407 | O61: 219115 | P61: 0 | Q61: 0 | R61: 0 | Y61: 35000 | AA61: 631111 | AB61: 250000 | AF61: 215000 | AH61: 3716633 | AI61: 340320 | AJ61: 0 | AK61: 225164 | AL61: 30297 | AM61: 19300 | AN61: 83455 | AO61: 0 | AW61: 698536 | AX61: 3018097 | AY61: 0
A62: 16.435.477-6 | B62: F1 | C62: Rivera | D62: Zapata | E62: Julio Pablo | F62: Supervisor Relacionamiento Comunitario | G62: OUTSOURCING, Salar Blanco, Salar Blanco | H62: 100 | I62: 30 | J62: 44 | K62: 0 | L62: 3678639 | M62: 5489373 | N62: 5270258 | O62: 219115 | P62: 0 | Q62: 0 | R62: 0 | AH62: 5489373 | AI62: 384786 | AJ62: 0 | AK62: 257505 | AL62: 0 | AM62: 32936 | AN62: 328206 | AO62: 0 | AW62: 1003433 | AX62: 4485940 | AY62: 0
A63: 13.973.575-7 | B63: F1 | C63: Rojas | D63: Malebran | E63: Angelo Mauricio | F63: Contador Financiero | G63: OUTSOURCING, Goldfields, Goldfield | H63: 100 | I63: 30 | J63: 42 | K63: 0 | L63: 3678639 | M63: 4680929 | N63: 4461814 | O63: 219115 | P63: 0 | Q63: 0 | R63: 0 | AB63: 250000 | AF63: 250000 | AH63: 5180929 | AI63: 414583 | AJ63: 0 | AK63: 257505 | AL63: 31881 | AM63: 28086 | AN63: 215698 | AO63: 0 | AW63: 947753 | AX63: 4233176 | AY63: 0
A64: 17.115.492-8 | B64: F1 | C64: Rojas | D64: Vega | E64: Mayra Arlene | F64: Asesor Senior de Prevención de Riesgos | G64: OUTSOURCING, CODELCO, Modulo 2 | I64: 30 | J64: 42 | K64: 0 | L64: 3049793 | M64: 3049793 | N64: 2357345 | O64: 219115 | P64: 0 | Q64: 0 | R64: 0 | Y64: 100000 | AA64: 473333 | AB64: 300000 | AF64: 300000 | AH64: 3749793 | AI64: 343712 | AJ64: 0 | AK64: 213486 | AL64: 0 | AM64: 18299 | AN64: 73274 | AO64: 0 | AP64: 780000 | AS64: 79490 | AW64: 1508261 | AX64: 2241532 | AY64: 0
A65: 11.516.219-5 | B65: F1 | C65: Roman | D65: Muñoz | E65: Hugo Alfredo | F65: Especialista en Biodiversidad | G65: OUTSOURCING, Salar Blanco, Salar Blanco | H65: 100 | I65: 30 | J65: 40 | K65: 0 | L65: 3678639 | M65: 5142553 | N65: 4923438 | O65: 219115 | P65: 0 | Q65: 0 | R65: 0 | AH65: 5142553 | AI65: 420836 | AJ65: 0 | AK65: 257505 | AL65: 0 | AM65: 30855 | AN65: 276799 | AO65: 0 | AW65: 985995 | AX65: 4156558 | AY65: 0
A66: 16.213.156-7 | B66: F1 | C66: Sáez | D66: Correa | E66: Juan Pablo | F66: Gerente de Sistema y Tecnología | G66: Over Head, IT, IT | H66: 100 | I66: 30 | J66: 44 | K66: 0 | L66: 3180336 | M66: 3180336 | N66: 2961221 | O66: 219115 | P66: 0 | Q66: 0 | R66: 0 | AB66: 200000 | AF66: 200000 | AH66: 3580336 | AI66: 363830 | AJ66: 0 | AK66: 222624 | AL66: 42974 | AM66: 19082 | AN66: 78524 | AO66: 0 | AW66: 727034 | AX66: 2853302 | AY66: 0
A67: 15.014.481-7 | B67: F1 | C67: Sarria | D67: Briceño | E67: Manuel Brayan | F67: Ingeniero Senior | G67: OUTSOURCING, CODELCO, Modulo 2 | I67: 30 | J67: 42 | K67: 0 | L67: 3678639 | M67: 3768212 | N67: 3075764 | O67: 219115 | P67: 0 | Q67: 0 | R67: 0 | Y67: 100000 | AA67: 473333 | AB67: 387500 | AF67: 387500 | AH67: 4643212 | AI67: 414583 | AJ67: 0 | AK67: 257505 | AL67: 0 | AM67: 22609 | AN67: 121212 | AO67: 0 | AW67: 815909 | AX67: 3827303 | AY67: 0
A68: 17.754.059-5 | B68: F1 | C68: Schalchli | D68: Robinson | E68: Cristian Andres | F68: Ingeniero Gestión Integral Contratos (EGIC) | G68: OUTSOURCING, Salar Blanco, Salar Blanco | H68: 100 | I68: 30 | J68: 42 | K68: 0 | L68: 3161565 | M68: 3161565 | N68: 2942450 | O68: 219115 | P68: 0 | Q68: 0 | R68: 0 | AH68: 3161565 | AI68: 330700 | AJ68: 0 | AK68: 221310 | AL68: 0 | AM68: 0 | AN68: 84095 | AO68: 0 | AW68: 636105 | AX68: 2525460 | AY68: 0
A69: 19.685.657-9 | B69: F1 | C69: Staeding | D69: Del Río | E69: Cristhian Nicolás | F69: Especialista de Medio Ambiente | G69: OUTSOURCING, Salar Blanco, Salar Blanco | H69: 100 | I69: 30 | J69: 60 | K69: 0 | L69: 3678639 | M69: 3778030 | N69: 3558915 | O69: 219115 | P69: 0 | Q69: 0 | R69: 0 | AH69: 3778030 | AI69: 384786 | AJ69: 0 | AK69: 257505 | AL69: 0 | AM69: 22668 | AN69: 124376 | AO69: 0 | AW69: 789335 | AX69: 2988695 | AY69: 0
A70: 16.203.337-9 | B70: F1 | C70: Torreblanca | D70: Oyanedel | E70: Juan Pablo | F70: Administrador de Contrato | G70: OUTSOURCING, CODELCO, Modulo 2 | I70: 30 | J70: 42 | K70: 0 | L70: 2853558 | M70: 2853558 | N70: 2634443 | O70: 219115 | P70: 0 | Q70: 0 | R70: 0 | Y70: 100000 | AB70: 325000 | AF70: 325000 | AH70: 3603558 | AI70: 326447 | AJ70: 0 | AK70: 199749 | AL70: 0 | AM70: 17121 | AN70: 60150 | AO70: 0 | AP70: 250000 | AS70: 186501 | AV70: 17972 | AW70: 1057940 | AX70: 2545618 | AY70: 0
A71: 16.513.123-1 | B71: F1 | C71: Torres | D71: Perez | E71: Gonzalo Andres | F71: Ingeniero Proyectos | G71: OUTSOURCING, Enap, Enap | H71: 100 | I71: 30 | J71: 37 | K71: 0 | L71: 2501208 | M71: 2501208 | N71: 2282093 | O71: 219115 | P71: 0 | Q71: 0 | R71: 0 | AB71: 250000 | AF71: 250000 | AH71: 3001208 | AI71: 264628 | AJ71: 0 | AK71: 175085 | AL71: 0 | AM71: 15007 | AN71: 43169 | AO71: 0 | AV71: 20667 | AW71: 518556 | AX71: 2482652 | AY71: 0
A72: 16.403.006-7 | B72: F1 | C72: Trujillo | D72: Carrasco | E72: Joanett Angelica | F72: Risk Prevention Advisor | G72: OUTSOURCING, Endress Hauser, Endress Hauser | H72: 100 | I72: 29 | J72: 42 | K72: 0 | L72: 3235971 | M72: 3235971 | N72: 3016856 | O72: 219115 | P72: 0 | Q72: 0 | R72: 0 | AH72: 3235971 | AI72: 364694 | AJ72: 0 | AK72: 226518 | AL72: 0 | AM72: 19416 | AN72: 85358 | AO72: 0 | AW72: 695986 | AX72: 2539985 | AY72: 0
A73: 17.155.741-0 | B73: F1 | C73: Valdivia | D73: Contreras | E73: Paulo Matías | F73: Gestor de Costos y Presupuestos | G73: OUTSOURCING, Enap, Enap | H73: 100 | I73: 30 | J73: 36 | K73: 0 | L73: 2399470 | M73: 2399470 | N73: 2180355 | O73: 219115 | P73: 0 | Q73: 0 | R73: 0 | AB73: 240000 | AF73: 240000 | AH73: 2879470 | AI73: 274499 | AJ73: 0 | AK73: 167963 | AL73: 0 | AM73: 0 | AN73: 39590 | AO73: 0 | AW73: 482052 | AX73: 2397418 | AY73: 0
A74: 13.884.122-7 | B74: F1 | C74: Verdugo | D74: Ortiz | E74: Alvaro Eduardo | F74: Operador Tecnológico | G74: OUTSOURCING, Goldfields, Goldfield | H74: 100 | I74: 30 | J74: 40 | K74: 0 | L74: 3198955 | M74: 3198955 | N74: 2979840 | O74: 219115 | P74: 0 | Q74: 0 | R74: 0 | AH74: 3198955 | AI74: 365960 | AJ74: 0 | AK74: 223927 | AL74: 0 | AM74: 19194 | AN74: 82521 | AO74: 0 | AS74: 533720 | AW74: 1225322 | AX74: 1973633 | AY74: 0
AX76: =SUM(AX7:AX74) -> 165317013

Sheet EMPRESA DE SER...ORIOS G.A. SPA
A1: Libro: Remuneraciones
A2: Empresa: EMPRESA DE SERVICIOS TRANSITORIOS G.A. SPA (78.231.643-5)
A3: Periodo: Agosto 2026
A4: Fecha Generación: 28/08/2026 a las 02:47PM
A6: RUT | B6: CÓDIGO | C6: AP PATERNO | D6: AP MATERNO | E6: NOMBRES | F6: CARGO | G6: AREA | H6: CENTRO COSTO | I6: DÍAS TRABAJADOS | J6: HORAS SEMANALES | K6: HORAS NO TRABAJADAS | L6: BASE IMP. PREVISIÓN | M6: BASE IMP. CESANTÍA | N6: SUELDO BASE | O6: GRATIFICACIÓN | P6: APORTE ASISTENCIA | Q6: HORAS EXTRAS | R6: ASIGNACIÓN FAMILIAR | S6: ASIGNACIÓN POR TELETRABAJO | T6: ASIGNACIÓN SALA CUNA | U6: ASIGNACIÓN TELEFONÍA E INTERNET | V6: BONO | W6: BONO ESTUDIO | X6: BONO GESTIÓN | Y6: BONO INTERNET | Z6: BONO TELEFONIA | AA6: BONO TRIMESTRAL ACUERDO MARCO | AB6: COLACIÓN | AC6: COMISIONES | AD6: DIFERENCIA BONO | AE6: INCENTIVO TRIMESTRAL CUOTA 3 | AF6: MOVILIZACIÓN | AG6: VIATICO | AH6: TOTAL HABERES | AI6: PREVIS | AJ6: APV | AK6: SALUD | AL6: SALUD VOLUNTARIA | AM6: CESANTÍA | AN6: IMPUESTO | AO6: CUENTA_2 | AP6: ANTICIPO DE REMUNERACIONES | AQ6: CONVENIO FALP | AR6: CUENTA 2 PESOS | AS6: CRÉDITO PERSONAL CAJA LOS ANDES | AT6: PRESTAMO EMPRESA | AU6: PRÉSTAMO EMPRESA | AV6: SEGURO DE VIDA CAJA LOS ANDES | AW6: TOTAL DESCUENTOS | AX6: SUELDO LÍQUIDO | AY6: SOBREGIRO
A7: 20.162.327-8 | B7: F1 | C7: Charrie | D7: Troncoso | E7: Javiera Ignacia | F7: Key Account Executive | G7: OUTSOURCING, EDGEWELL CHILE, EDGEWELL CHILE | H7: 100 | I7: 30 | J7: 40 | K7: 0 | L7: 3157134 | M7: 3157134 | N7: 2338019 | O7: 219115 | P7: 0 | Q7: 0 | R7: 0 | S7: 10000 | V7: 600000 | Z7: 20000 | AF7: 220000 | AH7: 3407134 | AI7: 334025 | AJ7: 0 | AK7: 220999 | AL7: 0 | AM7: 0 | AN7: 83500 | AO7: 0 | AW7: 638524 | AX7: 2768610 | AY7: 0
A8: 20.722.232-1 | B8: F1 | C8: Nordin | D8: Campos | E8: Antonia Belen | F8: SALES ENABLEMENT REP SUPPORT | G8: GA EST, Endress Hauser, Endress Hauser | H8: 100 | I8: 30 | J8: 40 | K8: 0 | L8: 990000 | M8: 990000 | N8: 792000 | O8: 198000 | P8: 0 | Q8: 0 | R8: 0 | AH8: 990000 | AI8: 104742 | AJ8: 0 | AK8: 69300 | AL8: 0 | AM8: 0 | AN8: 0 | AO8: 0 | AW8: 174042 | AX8: 815958 | AY8: 0
A9: 26.591.232-k | B9: F1 | C9: Ortega | D9: Paredes | E9: Gabriela Mercedes | F9: Ejecutivo(a) Comercial | G9: GA EST, Schindler, Schindler | H9: 100 | I9: 30 | J9: 42 | K9: 0 | L9: 3041378 | M9: 3041378 | N9: 1000000 | O9: 219115 | P9: 0 | Q9: 0 | R9: 0 | AB9: 120000 | AC9: 1822263 | AF9: 60000 | AH9: 3221378 | AI9: 348238 | AJ9: 0 | AK9: 212896 | AL9: 0 | AM9: 0 | AN9: 73750 | AO9: 0 | AP9: 200000 | AW9: 834884 | AX9: 2386494 | AY9: 0
A10: 16.628.617-4 | B10: F1 | C10: Palma | D10: Campos | E10: Cecilia Tamara | F10: Receptionist & Administrative Assistant | G10: GA EST, Endress Hauser, Endress Hauser | H10: 100 | I10: 30 | J10: 40 | K10: 0 | L10: 1690647 | M10: 1690647 | N10: 1471532 | O10: 219115 | P10: 0 | Q10: 0 | R10: 0 | AH10: 1690647 | AI10: 178870 | AJ10: 0 | AK10: 118345 | AL10: 0 | AM10: 0 | AN10: 17047 | AO10: 0 | AW10: 314262 | AX10: 1376385 | AY10: 0
A11: 22.647.597-4 | B11: F1 | C11: Videla | D11: Lopez | E11: Josefa Alejandra | F11: Accounts Assistant | G11: GA EST, Endress Hauser, Endress Hauser | H11: 100 | I11: 30 | J11: 40 | K11: 0 | L11: 691941 | M11: 691941 | N11: 553553 | O11: 138388 | P11: 0 | Q11: 0 | R11: 0 | AH11: 691941 | AI11: 72377 | AJ11: 0 | AK11: 48436 | AL11: 0 | AM11: 0 | AN11: 0 | AO11: 0 | AW11: 120813 | AX11: 571128 | AY11: 0
AX13: =SUM(AX7:AX11) -> 7918575
